{
  "updated": "2026-07-08T06:10:30Z",
  "market": {
    "kospi": {
      "price": 7281.1,
      "change": -375.21,
      "pct": -4.9,
      "high": 7791.66,
      "low": 7186.21,
      "vol": 467233000,
      "candles": [
        {
          "time": 1782950400,
          "open": 7933.1,
          "high": 8136.28,
          "low": 7616.33,
          "close": 7648.09,
          "vol": 505157
        },
        {
          "time": 1783036800,
          "open": 7739.75,
          "high": 8136.28,
          "low": 7378.1,
          "close": 8088.34,
          "vol": 465821
        },
        {
          "time": 1783296000,
          "open": 8186.82,
          "high": 8327.26,
          "low": 7815.53,
          "close": 8051.33,
          "vol": 448691
        },
        {
          "time": 1783382400,
          "open": 7919.2,
          "high": 7954.55,
          "low": 7389.22,
          "close": 7656.31,
          "vol": 516366
        },
        {
          "time": 1783468800,
          "open": 7452.48,
          "high": 7791.66,
          "low": 7186.21,
          "close": 7274.95,
          "vol": 466610
        }
      ]
    },
    "kosdaq": {
      "price": 788.14,
      "change": -43.09,
      "pct": -5.18,
      "high": 823.33,
      "low": 778.7,
      "vol": 540007000,
      "candles": [
        {
          "time": 1782950400,
          "open": 904.53,
          "high": 904.53,
          "low": 863.74,
          "close": 866.72,
          "vol": 560644
        },
        {
          "time": 1783036800,
          "open": 875.18,
          "high": 875.39,
          "low": 823.98,
          "close": 868.41,
          "vol": 601113
        },
        {
          "time": 1783296000,
          "open": 866.4,
          "high": 872.12,
          "low": 825.73,
          "close": 847.07,
          "vol": 535135
        },
        {
          "time": 1783382400,
          "open": 843.74,
          "high": 866.59,
          "low": 812.7,
          "close": 831.23,
          "vol": 543545
        },
        {
          "time": 1783468800,
          "open": 816.39,
          "high": 823.33,
          "low": 778.7,
          "close": 787.36,
          "vol": 539338
        }
      ]
    },
    "sp500": {
      "price": 7503.85,
      "change": -33.5802,
      "pct": -0.45,
      "high": 7536.06,
      "low": 7478.63,
      "vol": 2991356000,
      "candles": [
        {
          "time": 1782826200,
          "open": 7441.27,
          "high": 7508.29,
          "low": 7438.04,
          "close": 7499.3599,
          "vol": 6037540000
        },
        {
          "time": 1782912600,
          "open": 7478.8398,
          "high": 7521.8101,
          "low": 7449.6299,
          "close": 7483.23,
          "vol": 5782730000
        },
        {
          "time": 1782999000,
          "open": 7495.1401,
          "high": 7540.75,
          "low": 7427.5498,
          "close": 7483.2402,
          "vol": 5463520000
        },
        {
          "time": 1783344600,
          "open": 7506.96,
          "high": 7551.3101,
          "low": 7500.9702,
          "close": 7537.4302,
          "vol": 4971110000
        },
        {
          "time": 1783431000,
          "open": 7516.6299,
          "high": 7536.0601,
          "low": 7478.6299,
          "close": 7503.8501,
          "vol": 5049590000
        }
      ]
    },
    "nasdaq": {
      "price": 25818.69,
      "change": -302.4702,
      "pct": -1.16,
      "high": 26010.023,
      "low": 25684.15,
      "vol": 7215704000,
      "candles": [
        {
          "time": 1782826200,
          "open": 25824.4707,
          "high": 26253.0391,
          "low": 25808.0605,
          "close": 26213.7207,
          "vol": 9809990000
        },
        {
          "time": 1782912600,
          "open": 26039.5098,
          "high": 26238.0605,
          "low": 25954.4609,
          "close": 26040.0293,
          "vol": 9094410000
        },
        {
          "time": 1782999000,
          "open": 26047.3809,
          "high": 26261.0898,
          "low": 25630.5098,
          "close": 25832.6699,
          "vol": 9529580000
        },
        {
          "time": 1783344600,
          "open": 25999.6094,
          "high": 26209.7598,
          "low": 25963.4395,
          "close": 26121.1602,
          "vol": 7827050000
        },
        {
          "time": 1783431000,
          "open": 25960.1309,
          "high": 26010.0195,
          "low": 25684.1504,
          "close": 25818.6895,
          "vol": 8244680000
        }
      ]
    },
    "dow": {
      "price": 52925.15,
      "change": -130.7602,
      "pct": -0.25,
      "high": 53289.3,
      "low": 52774.17,
      "vol": 443184789,
      "candles": [
        {
          "time": 1782826200,
          "open": 52168.1797,
          "high": 52387.4492,
          "low": 52033.1289,
          "close": 52319.1992,
          "vol": 622980000
        },
        {
          "time": 1782912600,
          "open": 52231.1797,
          "high": 52742.6602,
          "low": 52026.6406,
          "close": 52305.2383,
          "vol": 622970000
        },
        {
          "time": 1782999000,
          "open": 52395.2188,
          "high": 52903.8516,
          "low": 52395.2188,
          "close": 52900.0703,
          "vol": 548820000
        },
        {
          "time": 1783344600,
          "open": 52828.4492,
          "high": 53060.1016,
          "low": 52648.6914,
          "close": 53055.9102,
          "vol": 467390000
        },
        {
          "time": 1783431000,
          "open": 53104.0586,
          "high": 53289.3008,
          "low": 52774.1719,
          "close": 52925.1484,
          "vol": 442010000
        }
      ]
    },
    "ndx": {
      "price": 29173.018,
      "change": -524.8511,
      "pct": -1.77,
      "high": 29426.45,
      "low": 28974.47,
      "vol": 1377782000,
      "candles": [
        {
          "time": 1782826200,
          "open": 29792.9297,
          "high": 30328.7891,
          "low": 29767.7598,
          "close": 30276.3496,
          "vol": 9809990000
        },
        {
          "time": 1782912600,
          "open": 29914.2793,
          "high": 30084.7793,
          "low": 29787.4102,
          "close": 29809.1309,
          "vol": 9094410000
        },
        {
          "time": 1782999000,
          "open": 29778.6992,
          "high": 30044.5,
          "low": 29087.3301,
          "close": 29329.2109,
          "vol": 9529580000
        },
        {
          "time": 1783344600,
          "open": 29575.5703,
          "high": 29847.7402,
          "low": 29553.6191,
          "close": 29697.8691,
          "vol": 7827050000
        },
        {
          "time": 1783431000,
          "open": 29362.1992,
          "high": 29426.4492,
          "low": 28974.4707,
          "close": 29173.0195,
          "vol": 8244680000
        }
      ]
    },
    "vix": {
      "price": 16.13,
      "change": 0.56,
      "pct": 3.6,
      "high": 0.0,
      "low": 0.0,
      "vol": 0,
      "candles": [
        {
          "time": 1782826200,
          "open": 17.54,
          "high": 17.75,
          "low": 16.27,
          "close": 16.45,
          "vol": 0
        },
        {
          "time": 1782912600,
          "open": 17.11,
          "high": 17.3,
          "low": 15.97,
          "close": 16.59,
          "vol": 0
        },
        {
          "time": 1782999000,
          "open": 17.05,
          "high": 17.21,
          "low": 15.79,
          "close": 16.15,
          "vol": 0
        },
        {
          "time": 1783344600,
          "open": 16.4,
          "high": 16.5,
          "low": 15.56,
          "close": 15.57,
          "vol": 0
        },
        {
          "time": 1783431000,
          "open": 15.87,
          "high": 16.64,
          "low": 15.53,
          "close": 16.13,
          "vol": 0
        }
      ]
    },
    "dxy": {
      "price": 101.051,
      "change": -0.089,
      "pct": -0.09,
      "high": 101.215,
      "low": 101.037,
      "vol": 0,
      "candles": [
        {
          "time": 1782964800,
          "open": 101.4,
          "high": 101.43,
          "low": 100.56,
          "close": 100.86,
          "vol": 0
        },
        {
          "time": 1783310400,
          "open": 100.86,
          "high": 101.15,
          "low": 100.83,
          "close": 100.85,
          "vol": 0
        },
        {
          "time": 1783396800,
          "open": 100.84,
          "high": 101.15,
          "low": 100.8,
          "close": 101.14,
          "vol": 0
        },
        {
          "time": 1783483200,
          "open": 101.158,
          "high": 101.215,
          "low": 101.037,
          "close": 101.051,
          "vol": 0
        }
      ]
    },
    "usdkrw": {
      "price": 1506.68,
      "change": -22.08,
      "pct": -1.44,
      "high": 1522.08,
      "low": 1502.28,
      "vol": 0,
      "candles": [
        {
          "time": 1782946800,
          "open": 1551.4,
          "high": 1556.53,
          "low": 1537.1899,
          "close": 1551.8101,
          "vol": 0
        },
        {
          "time": 1783033200,
          "open": 1544.52,
          "high": 1547.65,
          "low": 1525.38,
          "close": 1542.13,
          "vol": 0
        },
        {
          "time": 1783292400,
          "open": 1531.58,
          "high": 1536.55,
          "low": 1526.14,
          "close": 1531.0,
          "vol": 0
        },
        {
          "time": 1783378800,
          "open": 1528.3,
          "high": 1531.5601,
          "low": 1509.86,
          "close": 1528.76,
          "vol": 0
        },
        {
          "time": 1783490858,
          "open": 1512.85,
          "high": 1522.08,
          "low": 1502.28,
          "close": 1506.6801,
          "vol": 0
        }
      ]
    },
    "jpykrw": {
      "price": 9.269,
      "change": -0.1594,
      "pct": -1.69,
      "high": 9.339,
      "low": 9.243,
      "vol": 0,
      "candles": [
        {
          "time": 1782946800,
          "open": 9.5452,
          "high": 9.6113,
          "low": 9.5362,
          "close": 9.5536,
          "vol": 0
        },
        {
          "time": 1783033200,
          "open": 9.5441,
          "high": 9.593,
          "low": 9.4842,
          "close": 9.5616,
          "vol": 0
        },
        {
          "time": 1783292400,
          "open": 9.4831,
          "high": 9.5092,
          "low": 9.4224,
          "close": 9.4778,
          "vol": 0
        },
        {
          "time": 1783378800,
          "open": 9.4218,
          "high": 9.4448,
          "low": 9.3327,
          "close": 9.4284,
          "vol": 0
        },
        {
          "time": 1783490731,
          "open": 9.307,
          "high": 9.339,
          "low": 9.243,
          "close": 9.269,
          "vol": 0
        }
      ]
    },
    "eurkrw": {
      "price": 1721.0,
      "change": -27.3101,
      "pct": -1.56,
      "high": 1732.5,
      "low": 1716.2,
      "vol": 0,
      "candles": [
        {
          "time": 1782946800,
          "open": 1766.13,
          "high": 1771.01,
          "low": 1759.14,
          "close": 1765.89,
          "vol": 0
        },
        {
          "time": 1783033200,
          "open": 1763.67,
          "high": 1767.5699,
          "low": 1747.3199,
          "close": 1755.52,
          "vol": 0
        },
        {
          "time": 1783292400,
          "open": 1754.14,
          "high": 1754.15,
          "low": 1745.9301,
          "close": 1746.86,
          "vol": 0
        },
        {
          "time": 1783378800,
          "open": 1748.3,
          "high": 1750.36,
          "low": 1725.77,
          "close": 1748.3101,
          "vol": 0
        },
        {
          "time": 1783490731,
          "open": 1724.9,
          "high": 1732.5,
          "low": 1716.2,
          "close": 1721.0,
          "vol": 0
        }
      ]
    },
    "gbpkrw": {
      "price": 2012.01,
      "change": -35.167,
      "pct": -1.72,
      "high": 2026.5,
      "low": 2006.44,
      "vol": 0,
      "candles": [
        {
          "time": 1782946800,
          "open": 2060.3784,
          "high": 2068.8486,
          "low": 2054.3452,
          "close": 2062.0256,
          "vol": 0
        },
        {
          "time": 1783033200,
          "open": 2055.2935,
          "high": 2066.1633,
          "low": 2040.3253,
          "close": 2059.1379,
          "vol": 0
        },
        {
          "time": 1783292400,
          "open": 2044.5851,
          "high": 2050.5911,
          "low": 2037.0422,
          "close": 2043.478,
          "vol": 0
        },
        {
          "time": 1783378800,
          "open": 2045.6478,
          "high": 2051.0791,
          "low": 2022.0466,
          "close": 2047.177,
          "vol": 0
        },
        {
          "time": 1783490731,
          "open": 2018.13,
          "high": 2026.5,
          "low": 2006.4399,
          "close": 2012.01,
          "vol": 0
        }
      ]
    },
    "cnykrw": {
      "price": 221.92,
      "change": -0.635,
      "pct": -0.29,
      "high": 223.602,
      "low": 221.277,
      "vol": 0,
      "candles": [
        {
          "time": 1783490731,
          "open": 222.783,
          "high": 223.602,
          "low": 221.277,
          "close": 221.92,
          "vol": 0
        }
      ]
    },
    "oil": {
      "price": 72.75,
      "change": 2.31,
      "pct": 3.28,
      "high": 72.92,
      "low": 71.75,
      "vol": 27373,
      "candles": [
        {
          "time": 1782964800,
          "open": 68.03,
          "high": 68.8,
          "low": 67.04,
          "close": 68.69,
          "vol": 183635
        },
        {
          "time": 1783310400,
          "open": 68.68,
          "high": 69.21,
          "low": 67.82,
          "close": 68.55,
          "vol": 229909
        },
        {
          "time": 1783396800,
          "open": 68.58,
          "high": 72.51,
          "low": 68.58,
          "close": 70.44,
          "vol": 229909
        },
        {
          "time": 1783483200,
          "open": 72.38,
          "high": 72.92,
          "low": 71.75,
          "close": 72.75,
          "vol": 27373
        }
      ]
    },
    "brent": {
      "price": 76.57,
      "change": 2.41,
      "pct": 3.25,
      "high": 76.75,
      "low": 75.45,
      "vol": 5024,
      "candles": [
        {
          "time": 1782964800,
          "open": 71.09,
          "high": 71.91,
          "low": 70.14,
          "close": 71.8,
          "vol": 0
        },
        {
          "time": 1783310400,
          "open": 71.87,
          "high": 72.59,
          "low": 71.03,
          "close": 71.99,
          "vol": 46238
        },
        {
          "time": 1783396800,
          "open": 72.11,
          "high": 76.35,
          "low": 72.06,
          "close": 74.16,
          "vol": 46238
        },
        {
          "time": 1783483200,
          "open": 75.99,
          "high": 76.75,
          "low": 75.45,
          "close": 76.57,
          "vol": 5024
        }
      ]
    },
    "gold": {
      "price": 4139.9,
      "change": -5.3998,
      "pct": -0.13,
      "high": 4144.6,
      "low": 4104.0,
      "vol": 25306,
      "candles": [
        {
          "time": 1782964800,
          "open": 4067.5,
          "high": 4140.1001,
          "low": 4062.0,
          "close": 4112.7002,
          "vol": 228
        },
        {
          "time": 1783310400,
          "open": 4175.3999,
          "high": 4199.7002,
          "low": 4134.2002,
          "close": 4155.1001,
          "vol": 1024
        },
        {
          "time": 1783396800,
          "open": 4126.5,
          "high": 4167.2002,
          "low": 4107.2002,
          "close": 4145.2998,
          "vol": 1024
        },
        {
          "time": 1783483200,
          "open": 4106.5,
          "high": 4144.6001,
          "low": 4104.0,
          "close": 4139.8999,
          "vol": 25306
        }
      ]
    },
    "silver": {
      "price": 61.31,
      "change": 0.379,
      "pct": 0.62,
      "high": 61.395,
      "low": 60.01,
      "vol": 6884,
      "candles": [
        {
          "time": 1782964800,
          "open": 59.47,
          "high": 61.595,
          "low": 59.465,
          "close": 60.643,
          "vol": 197
        },
        {
          "time": 1783310400,
          "open": 62.62,
          "high": 62.62,
          "low": 61.635,
          "close": 61.92,
          "vol": 69
        },
        {
          "time": 1783396800,
          "open": 61.205,
          "high": 61.37,
          "low": 60.205,
          "close": 60.931,
          "vol": 69
        },
        {
          "time": 1783483200,
          "open": 60.31,
          "high": 61.395,
          "low": 60.01,
          "close": 61.31,
          "vol": 6884
        }
      ]
    },
    "natgas": {
      "price": 3.28,
      "change": 0.015,
      "pct": 0.46,
      "high": 3.286,
      "low": 3.267,
      "vol": 2462,
      "candles": [
        {
          "time": 1782964800,
          "open": 3.214,
          "high": 3.22,
          "low": 3.151,
          "close": 3.196,
          "vol": 137589
        },
        {
          "time": 1783310400,
          "open": 3.206,
          "high": 3.256,
          "low": 3.159,
          "close": 3.245,
          "vol": 205853
        },
        {
          "time": 1783396800,
          "open": 3.254,
          "high": 3.32,
          "low": 3.181,
          "close": 3.265,
          "vol": 205853
        },
        {
          "time": 1783483200,
          "open": 3.281,
          "high": 3.286,
          "low": 3.267,
          "close": 3.28,
          "vol": 2462
        }
      ]
    },
    "copper": {
      "price": 6.215,
      "change": 0.0435,
      "pct": 0.7,
      "high": 6.219,
      "low": 6.16,
      "vol": 4191,
      "candles": [
        {
          "time": 1782964800,
          "open": 6.104,
          "high": 6.1545,
          "low": 6.07,
          "close": 6.1145,
          "vol": 1080
        },
        {
          "time": 1783310400,
          "open": 6.1545,
          "high": 6.2005,
          "low": 6.147,
          "close": 6.178,
          "vol": 1021
        },
        {
          "time": 1783396800,
          "open": 6.169,
          "high": 6.205,
          "low": 6.117,
          "close": 6.1715,
          "vol": 1021
        },
        {
          "time": 1783483200,
          "open": 6.1825,
          "high": 6.219,
          "low": 6.1595,
          "close": 6.2155,
          "vol": 4191
        }
      ]
    },
    "us10y": {
      "price": 4.529,
      "change": 0.044,
      "pct": 0.98,
      "high": 0.0,
      "low": 0.0,
      "vol": 0,
      "candles": [
        {
          "time": 1782822000,
          "open": 4.392,
          "high": 4.422,
          "low": 4.388,
          "close": 4.418,
          "vol": 0
        },
        {
          "time": 1782908400,
          "open": 4.483,
          "high": 4.501,
          "low": 4.457,
          "close": 4.475,
          "vol": 0
        },
        {
          "time": 1782994800,
          "open": 4.503,
          "high": 4.505,
          "low": 4.453,
          "close": 4.485,
          "vol": 0
        },
        {
          "time": 1783426800,
          "open": 4.497,
          "high": 4.533,
          "low": 4.485,
          "close": 4.529,
          "vol": 0
        }
      ]
    },
    "us30y": {
      "price": 5.043,
      "change": 0.058,
      "pct": 1.16,
      "high": 0.0,
      "low": 0.0,
      "vol": 0,
      "candles": [
        {
          "time": 1782822000,
          "open": 4.874,
          "high": 4.907,
          "low": 4.873,
          "close": 4.902,
          "vol": 0
        },
        {
          "time": 1782908400,
          "open": 4.977,
          "high": 4.99,
          "low": 4.954,
          "close": 4.966,
          "vol": 0
        },
        {
          "time": 1782994800,
          "open": 4.993,
          "high": 4.997,
          "low": 4.96,
          "close": 4.985,
          "vol": 0
        },
        {
          "time": 1783426800,
          "open": 5.011,
          "high": 5.045,
          "low": 5.002,
          "close": 5.043,
          "vol": 0
        }
      ]
    },
    "nvda": {
      "price": 196.93,
      "change": 1.38,
      "pct": 0.71,
      "high": 198.41,
      "low": 191.15,
      "vol": 122600973,
      "candles": [
        {
          "time": 1782826200,
          "open": 197.24,
          "high": 200.63,
          "low": 195.11,
          "close": 200.09,
          "vol": 166476700
        },
        {
          "time": 1782912600,
          "open": 196.2,
          "high": 199.85,
          "low": 193.45,
          "close": 197.58,
          "vol": 146147600
        },
        {
          "time": 1782999000,
          "open": 197.14,
          "high": 200.06,
          "low": 192.35,
          "close": 194.83,
          "vol": 142068700
        },
        {
          "time": 1783344600,
          "open": 194.42,
          "high": 197.55,
          "low": 193.99,
          "close": 195.55,
          "vol": 108999000
        },
        {
          "time": 1783431000,
          "open": 192.37,
          "high": 198.41,
          "low": 191.14,
          "close": 196.93,
          "vol": 123810500
        }
      ]
    },
    "aapl": {
      "price": 310.66,
      "change": -2.0,
      "pct": -0.64,
      "high": 315.48,
      "low": 310.15,
      "vol": 42083263,
      "candles": [
        {
          "time": 1782826200,
          "open": 281.17,
          "high": 289.94,
          "low": 280.7,
          "close": 289.36,
          "vol": 65100200
        },
        {
          "time": 1782912600,
          "open": 293.44,
          "high": 296.59,
          "low": 289.2,
          "close": 294.38,
          "vol": 50164200
        },
        {
          "time": 1782999000,
          "open": 294.12,
          "high": 309.42,
          "low": 293.68,
          "close": 308.63,
          "vol": 75352800
        },
        {
          "time": 1783344600,
          "open": 307.36,
          "high": 314.2,
          "low": 307.0,
          "close": 312.66,
          "vol": 53590000
        },
        {
          "time": 1783431000,
          "open": 315.29,
          "high": 315.48,
          "low": 310.15,
          "close": 310.66,
          "vol": 42426500
        }
      ]
    },
    "msft": {
      "price": 388.84,
      "change": 2.1,
      "pct": 0.54,
      "high": 395.57,
      "low": 388.22,
      "vol": 28958589,
      "candles": [
        {
          "time": 1782826200,
          "open": 371.03,
          "high": 374.15,
          "low": 367.45,
          "close": 373.02,
          "vol": 44945700
        },
        {
          "time": 1782912600,
          "open": 380.83,
          "high": 388.83,
          "low": 374.89,
          "close": 384.28,
          "vol": 48065800
        },
        {
          "time": 1782999000,
          "open": 384.48,
          "high": 392.2,
          "low": 383.7,
          "close": 390.49,
          "vol": 42128900
        },
        {
          "time": 1783344600,
          "open": 387.04,
          "high": 389.15,
          "low": 381.22,
          "close": 386.74,
          "vol": 34224500
        },
        {
          "time": 1783431000,
          "open": 392.49,
          "high": 395.57,
          "low": 388.22,
          "close": 388.84,
          "vol": 29209100
        }
      ]
    },
    "tsla": {
      "price": 402.9,
      "change": -16.87,
      "pct": -4.02,
      "high": 419.55,
      "low": 401.88,
      "vol": 37962643,
      "candles": [
        {
          "time": 1782826200,
          "open": 406.0,
          "high": 424.54,
          "low": 406.0,
          "close": 420.6,
          "vol": 43385600
        },
        {
          "time": 1782912600,
          "open": 421.46,
          "high": 432.86,
          "low": 418.09,
          "close": 425.3,
          "vol": 40127900
        },
        {
          "time": 1782999000,
          "open": 428.01,
          "high": 432.35,
          "low": 389.3,
          "close": 393.45,
          "vol": 73717700
        },
        {
          "time": 1783344600,
          "open": 397.5,
          "high": 420.0,
          "low": 390.5,
          "close": 419.77,
          "vol": 54727900
        },
        {
          "time": 1783431000,
          "open": 416.96,
          "high": 419.56,
          "low": 401.88,
          "close": 402.9,
          "vol": 38043200
        }
      ]
    },
    "googl": {
      "price": 367.03,
      "change": 0.57,
      "pct": 0.16,
      "high": 373.16,
      "low": 365.5,
      "vol": 23927397,
      "candles": [
        {
          "time": 1782826200,
          "open": 353.87,
          "high": 358.62,
          "low": 350.4,
          "close": 357.37,
          "vol": 35237200
        },
        {
          "time": 1782912600,
          "open": 358.37,
          "high": 362.97,
          "low": 356.43,
          "close": 361.21,
          "vol": 26736400
        },
        {
          "time": 1782999000,
          "open": 359.48,
          "high": 364.21,
          "low": 353.42,
          "close": 359.91,
          "vol": 25974800
        },
        {
          "time": 1783344600,
          "open": 361.55,
          "high": 367.93,
          "low": 357.38,
          "close": 366.46,
          "vol": 26915800
        },
        {
          "time": 1783431000,
          "open": 369.07,
          "high": 373.16,
          "low": 365.5,
          "close": 367.03,
          "vol": 24008000
        }
      ]
    },
    "meta": {
      "price": 615.58,
      "change": 15.29,
      "pct": 2.55,
      "high": 625.37,
      "low": 603.66,
      "vol": 18215095,
      "candles": [
        {
          "time": 1782826200,
          "open": 560.94,
          "high": 565.54,
          "low": 551.43,
          "close": 563.29,
          "vol": 18111100
        },
        {
          "time": 1782912600,
          "open": 607.91,
          "high": 628.28,
          "low": 595.1,
          "close": 612.91,
          "vol": 45536300
        },
        {
          "time": 1782999000,
          "open": 607.9,
          "high": 610.0,
          "low": 580.42,
          "close": 582.9,
          "vol": 21705900
        },
        {
          "time": 1783344600,
          "open": 594.84,
          "high": 603.58,
          "low": 581.76,
          "close": 600.29,
          "vol": 17674100
        },
        {
          "time": 1783431000,
          "open": 607.59,
          "high": 625.37,
          "low": 603.66,
          "close": 615.58,
          "vol": 18524000
        }
      ]
    },
    "spy": {
      "price": 747.71,
      "change": -3.57,
      "pct": -0.48,
      "high": 750.96,
      "low": 745.21,
      "vol": 40095496,
      "candles": [
        {
          "time": 1782826200,
          "open": 741.29,
          "high": 748.02,
          "low": 740.89,
          "close": 746.77,
          "vol": 55626000
        },
        {
          "time": 1782912600,
          "open": 745.0,
          "high": 749.44,
          "low": 742.38,
          "close": 745.76,
          "vol": 47100900
        },
        {
          "time": 1782999000,
          "open": 747.4,
          "high": 751.31,
          "low": 740.03,
          "close": 744.78,
          "vol": 57447800
        },
        {
          "time": 1783344600,
          "open": 748.74,
          "high": 752.41,
          "low": 747.41,
          "close": 751.28,
          "vol": 50673300
        },
        {
          "time": 1783431000,
          "open": 750.22,
          "high": 750.96,
          "low": 745.21,
          "close": 747.71,
          "vol": 43601100
        }
      ]
    },
    "qqq": {
      "price": 709.43,
      "change": -13.39,
      "pct": -1.85,
      "high": 716.34,
      "low": 704.9,
      "vol": 39999571,
      "candles": [
        {
          "time": 1782826200,
          "open": 724.18,
          "high": 737.62,
          "low": 723.91,
          "close": 736.4,
          "vol": 42121800
        },
        {
          "time": 1782912600,
          "open": 729.19,
          "high": 731.92,
          "low": 724.6,
          "close": 725.17,
          "vol": 40803800
        },
        {
          "time": 1782999000,
          "open": 725.58,
          "high": 730.83,
          "low": 707.56,
          "close": 712.6,
          "vol": 50959800
        },
        {
          "time": 1783344600,
          "open": 719.93,
          "high": 726.08,
          "low": 718.45,
          "close": 722.82,
          "vol": 30220400
        },
        {
          "time": 1783431000,
          "open": 714.17,
          "high": 716.35,
          "low": 704.9,
          "close": 709.43,
          "vol": 42150000
        }
      ]
    },
    "tlt": {
      "price": 84.55,
      "change": -0.9,
      "pct": -1.05,
      "high": 85.168,
      "low": 84.54,
      "vol": 24153794,
      "candles": [
        {
          "time": 1782826200,
          "open": 87.15,
          "high": 87.18,
          "low": 86.38,
          "close": 86.42,
          "vol": 31079500
        },
        {
          "time": 1782912600,
          "open": 85.48,
          "high": 85.79,
          "low": 85.43,
          "close": 85.52,
          "vol": 28109800
        },
        {
          "time": 1782999000,
          "open": 85.38,
          "high": 85.78,
          "low": 85.37,
          "close": 85.51,
          "vol": 20816300
        },
        {
          "time": 1783344600,
          "open": 85.43,
          "high": 85.48,
          "low": 85.18,
          "close": 85.45,
          "vol": 17940900
        },
        {
          "time": 1783431000,
          "open": 85.12,
          "high": 85.17,
          "low": 84.54,
          "close": 84.55,
          "vol": 24553800
        }
      ]
    },
    "gld": {
      "price": 377.49,
      "change": -4.64,
      "pct": -1.21,
      "high": 383.6,
      "low": 375.52,
      "vol": 4449661,
      "candles": [
        {
          "time": 1782826200,
          "open": 369.22,
          "high": 372.83,
          "low": 368.26,
          "close": 368.38,
          "vol": 5302100
        },
        {
          "time": 1782912600,
          "open": 371.21,
          "high": 377.78,
          "low": 370.21,
          "close": 370.6,
          "vol": 9058300
        },
        {
          "time": 1782999000,
          "open": 377.44,
          "high": 380.27,
          "low": 376.29,
          "close": 378.13,
          "vol": 7592900
        },
        {
          "time": 1783344600,
          "open": 380.21,
          "high": 382.43,
          "low": 378.83,
          "close": 382.13,
          "vol": 3906500
        },
        {
          "time": 1783431000,
          "open": 382.39,
          "high": 383.6,
          "low": 375.52,
          "close": 377.49,
          "vol": 4778100
        }
      ]
    },
    "eem": {
      "price": 65.72,
      "change": -1.85,
      "pct": -2.74,
      "high": 66.33,
      "low": 65.255,
      "vol": 26252855,
      "candles": [
        {
          "time": 1782826200,
          "open": 67.59,
          "high": 68.5,
          "low": 67.48,
          "close": 68.41,
          "vol": 20384300
        },
        {
          "time": 1782912600,
          "open": 66.91,
          "high": 67.46,
          "low": 66.48,
          "close": 66.48,
          "vol": 28146700
        },
        {
          "time": 1782999000,
          "open": 66.53,
          "high": 67.19,
          "low": 64.8,
          "close": 65.7,
          "vol": 34258700
        },
        {
          "time": 1783344600,
          "open": 67.25,
          "high": 67.79,
          "low": 67.21,
          "close": 67.57,
          "vol": 24039300
        },
        {
          "time": 1783431000,
          "open": 65.99,
          "high": 66.33,
          "low": 65.26,
          "close": 65.72,
          "vol": 26268900
        }
      ]
    },
    "xle": {
      "price": 54.64,
      "change": 1.51,
      "pct": 2.84,
      "high": 54.82,
      "low": 53.6,
      "vol": 39789494,
      "candles": [
        {
          "time": 1782826200,
          "open": 53.62,
          "high": 54.12,
          "low": 53.08,
          "close": 53.11,
          "vol": 28284000
        },
        {
          "time": 1782912600,
          "open": 53.05,
          "high": 53.44,
          "low": 52.62,
          "close": 52.81,
          "vol": 33662700
        },
        {
          "time": 1782999000,
          "open": 53.24,
          "high": 53.65,
          "low": 52.91,
          "close": 53.22,
          "vol": 28525600
        },
        {
          "time": 1783344600,
          "open": 53.06,
          "high": 53.55,
          "low": 53.0,
          "close": 53.13,
          "vol": 24735300
        },
        {
          "time": 1783431000,
          "open": 53.61,
          "high": 54.82,
          "low": 53.6,
          "close": 54.64,
          "vol": 41810900
        }
      ]
    },
    "samsung": {
      "price": 278750.0,
      "change": -17250.0,
      "pct": -5.83,
      "high": 300000.0,
      "low": 273500.0,
      "vol": 29727079,
      "candles": [
        {
          "time": 1782950400,
          "open": 290000.0,
          "high": 304000.0,
          "low": 281500.0,
          "close": 286000.0,
          "vol": 38905074
        },
        {
          "time": 1783036800,
          "open": 288500.0,
          "high": 313000.0,
          "low": 283500.0,
          "close": 309500.0,
          "vol": 31520538
        },
        {
          "time": 1783296000,
          "open": 320000.0,
          "high": 325000.0,
          "low": 303000.0,
          "close": 318000.0,
          "vol": 23872879
        },
        {
          "time": 1783382400,
          "open": 307000.0,
          "high": 310000.0,
          "low": 286000.0,
          "close": 296000.0,
          "vol": 32421032
        },
        {
          "time": 1783468800,
          "open": 285500.0,
          "high": 300000.0,
          "low": 273500.0,
          "close": 279000.0,
          "vol": 29700950
        }
      ]
    },
    "hynix": {
      "price": 2105000.0,
      "change": -96000.0,
      "pct": -4.36,
      "high": 2329000.0,
      "low": 2086000.0,
      "vol": 5848022,
      "candles": [
        {
          "time": 1782950400,
          "open": 2351000.0,
          "high": 2448000.0,
          "low": 2187000.0,
          "close": 2187000.0,
          "vol": 7685914
        },
        {
          "time": 1783036800,
          "open": 2197000.0,
          "high": 2454000.0,
          "low": 2045000.0,
          "close": 2425000.0,
          "vol": 7984914
        },
        {
          "time": 1783296000,
          "open": 2450000.0,
          "high": 2497000.0,
          "low": 2292000.0,
          "close": 2343000.0,
          "vol": 4235360
        },
        {
          "time": 1783382400,
          "open": 2289000.0,
          "high": 2343000.0,
          "low": 2080000.0,
          "close": 2201000.0,
          "vol": 6351195
        },
        {
          "time": 1783468800,
          "open": 2118000.0,
          "high": 2329000.0,
          "low": 2086000.0,
          "close": 2104000.0,
          "vol": 5835183
        }
      ]
    },
    "hanwha": {
      "price": 1026000.0,
      "change": -96000.0,
      "pct": -8.56,
      "high": 1139000.0,
      "low": 1007000.0,
      "vol": 148833,
      "candles": [
        {
          "time": 1782950400,
          "open": 1118000.0,
          "high": 1197000.0,
          "low": 1096000.0,
          "close": 1116000.0,
          "vol": 355677
        },
        {
          "time": 1783036800,
          "open": 1175000.0,
          "high": 1190000.0,
          "low": 1111000.0,
          "close": 1175000.0,
          "vol": 259176
        },
        {
          "time": 1783296000,
          "open": 1205000.0,
          "high": 1240000.0,
          "low": 1125000.0,
          "close": 1159000.0,
          "vol": 140971
        },
        {
          "time": 1783382400,
          "open": 1141000.0,
          "high": 1142000.0,
          "low": 1050000.0,
          "close": 1122000.0,
          "vol": 184231
        },
        {
          "time": 1783468800,
          "open": 1135000.0,
          "high": 1139000.0,
          "low": 1007000.0,
          "close": 1024000.0,
          "vol": 147504
        }
      ]
    },
    "lignex": {
      "price": 721000.0,
      "change": -78000.0,
      "pct": -9.76,
      "high": 833000.0,
      "low": 705000.0,
      "vol": 219099,
      "candles": [
        {
          "time": 1782950400,
          "open": 772000.0,
          "high": 785000.0,
          "low": 736000.0,
          "close": 762000.0,
          "vol": 131336
        },
        {
          "time": 1783036800,
          "open": 781000.0,
          "high": 808000.0,
          "low": 747000.0,
          "close": 800000.0,
          "vol": 215284
        },
        {
          "time": 1783296000,
          "open": 816000.0,
          "high": 853000.0,
          "low": 773000.0,
          "close": 815000.0,
          "vol": 166019
        },
        {
          "time": 1783382400,
          "open": 793000.0,
          "high": 847000.0,
          "low": 759000.0,
          "close": 799000.0,
          "vol": 183793
        },
        {
          "time": 1783468800,
          "open": 827000.0,
          "high": 833000.0,
          "low": 705000.0,
          "close": 720000.0,
          "vol": 218188
        }
      ]
    },
    "rainbow": {
      "price": 427500.0,
      "change": -32000.0,
      "pct": -6.96,
      "high": 454000.0,
      "low": 417500.0,
      "vol": 82371,
      "candles": [
        {
          "time": 1782950400,
          "open": 503000.0,
          "high": 505000.0,
          "low": 477000.0,
          "close": 485000.0,
          "vol": 107266
        },
        {
          "time": 1783036800,
          "open": 485500.0,
          "high": 493500.0,
          "low": 455000.0,
          "close": 492500.0,
          "vol": 81141
        },
        {
          "time": 1783296000,
          "open": 492500.0,
          "high": 504000.0,
          "low": 464750.0,
          "close": 480000.0,
          "vol": 46265
        },
        {
          "time": 1783382400,
          "open": 476500.0,
          "high": 493000.0,
          "low": 440500.0,
          "close": 459500.0,
          "vol": 74111
        },
        {
          "time": 1783468800,
          "open": 439500.0,
          "high": 454000.0,
          "low": 417500.0,
          "close": 427500.0,
          "vol": 81935
        }
      ]
    },
    "doosanrobo": {
      "price": 72800.0,
      "change": -6000.0,
      "pct": -7.61,
      "high": 76900.0,
      "low": 71500.0,
      "vol": 630691,
      "candles": [
        {
          "time": 1782950400,
          "open": 87000.0,
          "high": 87100.0,
          "low": 81600.0,
          "close": 83300.0,
          "vol": 682348
        },
        {
          "time": 1783036800,
          "open": 83300.0,
          "high": 84800.0,
          "low": 79000.0,
          "close": 84600.0,
          "vol": 524579
        },
        {
          "time": 1783296000,
          "open": 84500.0,
          "high": 85300.0,
          "low": 80100.0,
          "close": 82500.0,
          "vol": 425788
        },
        {
          "time": 1783382400,
          "open": 81800.0,
          "high": 82300.0,
          "low": 76100.0,
          "close": 78800.0,
          "vol": 601941
        },
        {
          "time": 1783468800,
          "open": 76000.0,
          "high": 76900.0,
          "low": 71500.0,
          "close": 72700.0,
          "vol": 629845
        }
      ]
    },
    "samsungbio": {
      "price": 1370000.0,
      "change": -52000.0,
      "pct": -3.66,
      "high": 1432000.0,
      "low": 1350000.0,
      "vol": 43142,
      "candles": [
        {
          "time": 1782950400,
          "open": 1397000.0,
          "high": 1450000.0,
          "low": 1353000.0,
          "close": 1406000.0,
          "vol": 65143
        },
        {
          "time": 1783036800,
          "open": 1438000.0,
          "high": 1460000.0,
          "low": 1401000.0,
          "close": 1421000.0,
          "vol": 54162
        },
        {
          "time": 1783296000,
          "open": 1421000.0,
          "high": 1422000.0,
          "low": 1373000.0,
          "close": 1405000.0,
          "vol": 35577
        },
        {
          "time": 1783382400,
          "open": 1391000.0,
          "high": 1426000.0,
          "low": 1376000.0,
          "close": 1422000.0,
          "vol": 51193
        },
        {
          "time": 1783468800,
          "open": 1420000.0,
          "high": 1432000.0,
          "low": 1350000.0,
          "close": 1367000.0,
          "vol": 42869
        }
      ]
    },
    "celltrion": {
      "price": 177200.0,
      "change": -1000.0,
      "pct": -0.56,
      "high": 183900.0,
      "low": 174700.0,
      "vol": 717569,
      "candles": [
        {
          "time": 1782950400,
          "open": 174600.0,
          "high": 183200.0,
          "low": 169000.0,
          "close": 176600.0,
          "vol": 712765
        },
        {
          "time": 1783036800,
          "open": 183700.0,
          "high": 188000.0,
          "low": 178600.0,
          "close": 183600.0,
          "vol": 853838
        },
        {
          "time": 1783296000,
          "open": 183400.0,
          "high": 185000.0,
          "low": 174300.0,
          "close": 175900.0,
          "vol": 527031
        },
        {
          "time": 1783382400,
          "open": 174600.0,
          "high": 178500.0,
          "low": 172700.0,
          "close": 178200.0,
          "vol": 624179
        },
        {
          "time": 1783468800,
          "open": 178300.0,
          "high": 183900.0,
          "low": 174700.0,
          "close": 176900.0,
          "vol": 716402
        }
      ]
    }
  },
  "news": [
    {
      "source": "매일경제",
      "category": "분석",
      "title": "구윤철 “경제대도약 원년 완성…하반기 경제성장전략 조만간 발표”",
      "link": "https://www.mk.co.kr/news/economy/12093144",
      "summary": "[배경/맥락] 구윤철 경제부총리가 경제대도약 원년을 완성하겠다는 의지를 표현하며 하반기 경제성장전략을 조만간 발표할 예정임을 밝혔다. [투자 시사점] 정부의 새로운 경제성장전략 발표는 정책 방향과 산업별 지원 계획을 구체화할 것으로 예상되므로, 투자자들은 발표"
    },
    {
      "source": "매일경제",
      "category": "분석",
      "title": "“혹 떼려다 혹 붙였네”…양도세 안내려 ‘엄마 친구’에 허위 매도한 2주택자",
      "link": "https://www.mk.co.kr/news/economy/12093092",
      "summary": "[배경/맥락] 양도세 부담을 피하기 위해 실제 소유권 이전 없이 명의만 타인에게 옮기는 허위 매도를 한 2주택자가 적발되었다.\n\n[투자 시사점] 부동산 양도세 회피 시도가 적발될 경우 가산세와 함께 형사 처벌까지 받을 수 있으므로 투자자들은 세법 준수의 중요성을 인"
    },
    {
      "source": "매일경제",
      "category": "분석",
      "title": "발언하는 경제부총리",
      "link": "https://www.mk.co.kr/news/economy/12093002",
      "summary": "# 경제부총리 발언 분석\n\n[배경/맥락] 경제부총리가 공식적으로 경제 현안에 대해 발언함으로써 정부의 경제정책 방향과 입장을 시장에 전달하고 있습니다.\n\n[투자 시사점] 투자자들은 경제부총리의 발언을 통해 향후 금리, 환율, 규제 정책 등 시장에 영향을 미칠 정책 신호"
    },
    {
      "source": "매일경제",
      "category": "분석",
      "title": "비상경제본부 회의 주재하는 경제부총리",
      "link": "https://www.mk.co.kr/news/economy/12093001",
      "summary": "[배경/맥락] 정부가 경제부총리 주재로 비상경제본부 회의를 개최했으며, 이는 현재 경제 상황에 대한 정부의 즉각적인 대응 필요성을 시사한다.\n\n[투자 시사점] 투자자들은 정부의 경제 정책 발표와 시장 안정화 조치에 주목해야 하며, 향후 공시되는 구체적인 대책이 주식·"
    },
    {
      "source": "파이낸셜뉴스",
      "category": "분석",
      "title": "출렁이는 증시에…주식형 줄고 채권형·MMF로 이동",
      "link": "https://www.fnnews.com/news/202607071543151006",
      "summary": "**[배경/맥락]** 증시의 변동성이 커지면서 투자자들이 위험자산인 주식형 펀드에서 자금을 빼내고 있습니다. **[투자 시사점]** 이는 투자자들이 상대적으로 안정적인 채권형 펀드와 단기 유동성이 우수한 MMF로 자산을 재배치하고 있음을 의미합니다."
    },
    {
      "source": "파이낸셜뉴스",
      "category": "분석",
      "title": "고장난 코스피, 32번째 사이드카·6번째 서킷브레이커 발동 [fn마감시황]",
      "link": "https://www.fnnews.com/news/202607071559294846",
      "summary": "[배경/맥락] 코스피가 32번째 사이드카와 6번째 서킷브레이커가 발동될 정도로 급락하며 시장 변동성이 극도로 높아진 상황입니다. [투자 시사점] 투자자들은 시장 급락 시 자동 거래 중단 장치가 작동하는 만큼 포지션 재점검과 손절 타이밍을 신중히 고려해야 합니다."
    },
    {
      "source": "파이낸셜뉴스",
      "category": "분석",
      "title": "서학개미도 반도체 쏠림…급락에도 순매수 상위 10개 중 6개",
      "link": "https://www.fnnews.com/news/202607071545407051",
      "summary": "**[배경/맥락]** 개인 해외투자자들이 반도체 종목에 집중 투자하고 있으며, 최근 주가 급락 상황에서도 상위 10개 순매수 종목 중 6개가 반도체 관련 기업인 것으로 나타났다.\n\n**[투자 시사점]** 이는 개인 투자자들이 반도체 섹터의 장기적 가치를 평가하고 있으나, 동시"
    },
    {
      "source": "파이낸셜뉴스",
      "category": "분석",
      "title": "'삼전·닉스'에만 몰린 빚투 10조...주가 급락에 투자자 날벼락",
      "link": "https://www.fnnews.com/news/202607071353137560",
      "summary": "**[배경/맥락]** 삼성전자와 닉스 두 종목에 집중된 약 10조 원대의 빚을 내서 투자한 자금이 주가 급락으로 인해 손실을 입고 있습니다.\n\n**[투자 시사점]** 이는 소수 종목에 대한 과도한 차입 투자의 위험성을 보여주며, 투자자들이 분산 투자와 리스크 관리의 중요성"
    },
    {
      "source": "파이낸셜뉴스",
      "category": "국제",
      "title": "日10년물 국채 금리 2.85%까지 치솟아..30년 만에 최고",
      "link": "https://www.fnnews.com/news/202607071617049075",
      "summary": "[배경/맥락] 일본의 10년물 국채 금리가 2.85%까지 상승하여 약 30년 만에 최고 수준에 도달했습니다. [투자 시사점] 이는 일본 금리 인상 기조 강화와 엔화 강세 가능성을 시사하므로, 투자자들은 엔화 자산 및 일본 채권 투자 시 금리 상승 리스크를 고려해야 합니다"
    },
    {
      "source": "파이낸셜뉴스",
      "category": "국제",
      "title": "아마존, AI 투자 위해 250억달러 회사채 발행",
      "link": "https://www.fnnews.com/news/202607072340528291",
      "summary": "**배경/맥락:** 아마존이 인공지능 사업 확대를 위해 250억 달러 규모의 회사채를 발행하기로 결정했습니다.\n\n**투자 시사점:** 이는 아마존이 AI 경쟁력 강화에 막대한 자본을 투입하겠다는 의지를 보여주며, 채권 발행으로 인한 부채 증가가 향후 재무 건전성과 수익성에 영향을"
    },
    {
      "source": "파이낸셜뉴스",
      "category": "국제",
      "title": "AI 투자에 수입 급증…美 무역적자 776억달러",
      "link": "https://www.fnnews.com/news/202607080013125083",
      "summary": "**[배경/맥락]** 미국의 AI 관련 수입이 급증하면서 무역적자가 776억 달러에 달했습니다.\n\n**[투자 시사점]** 이는 AI 산업 성장에 따른 반도체·장비 수입 증가로 인해 미국의 무역 불균형이 심화되고 있음을 의미하며, 향후 통상 정책 변화와 관련 기업들의 실적에 영향을 미"
    },
    {
      "source": "파이낸셜뉴스",
      "category": "국제",
      "title": "\"스페이스X, 문명 야망의 정점\" 투자은행들 매수 추천…주가는 급락",
      "link": "https://www.fnnews.com/news/202607080144344409",
      "summary": "[배경/맥락] 투자은행들이 스페이스X에 대해 매수 추천을 내렸으나 주가는 오히려 급락하는 역현상이 발생했다.\n\n[투자 시사점] 이는 애널리스트의 긍정적 평가와 시장의 실제 수요 사이에 괴리가 있음을 시사하며, 투자자들은 추천 의견만으로는 아닌 시장 심리와 기술적"
    },
    {
      "source": "Investing.com",
      "category": "속보",
      "title": "쓰촨커룬바이오텍 주식, 오늘 하락하는 이유?",
      "link": "https://kr.investing.com/news/stock-market-news/article-93CH-2008399",
      "summary": "# 쓰촨커룬바이오텍 주식 분석\n\n[배경/맥락] 쓰촨커룬바이오텍의 주가가 당일 하락세를 보이고 있으며, 이는 구체적인 악재나 시장 변화가 발생했음을 시사합니다.\n\n[투자 시사점] 투자자들은 해당 기업의 공시 자료, 산업 뉴스, 시장 전망 등을 확인하여"
    },
    {
      "source": "Investing.com",
      "category": "속보",
      "title": "텔레노어, 반호프 지배 지분 6억2970만 달러에 인수",
      "link": "https://kr.investing.com/news/stock-market-news/article-93CH-2008394",
      "summary": "[배경/맥락] 노르웨이 통신사 텔레노어가 반호프의 지배 지분을 약 6억3천만 달러에 인수하기로 결정했다.\n\n[투자 시사점] 이는 텔레노어의 포트폴리오 확장 및 시장 지배력 강화 전략으로, 인수 자금 조달 방식과 향후 통합 실적이 주가에 영향을 미칠 것으로 예상"
    },
    {
      "source": "Investing.com",
      "category": "속보",
      "title": "SK하이닉스 280억 달러 규모 美 상장, 견조한 수요 기록 (블룸버그)",
      "link": "https://kr.investing.com/news/stock-market-news/article-2008385",
      "summary": "[배경/맥락] SK하이닉스가 280억 달러 규모의 미국 상장을 진행했으며 견조한 수요를 기록했다.\n\n[투자 시사점] 이는 글로벌 반도체 수요 회복과 SK하이닉스의 자금 조달 능력이 시장에서 긍정적으로 평가되고 있음을 의미한다."
    },
    {
      "source": "Investing.com",
      "category": "속보",
      "title": "번스타인, 실적 시즌 앞두고 유럽 주요 항공사 선정",
      "link": "https://kr.investing.com/news/stock-market-news/article-93CH-2008382",
      "summary": "[배경/맥락] 번스타인이 실적 시즌을 앞두고 유럽 주요 항공사들을 선정했다.\n\n[투자 시사점] 이는 향후 항공사들의 실적 발표 시 긍정적 평가 가능성을 시사하며, 해당 항공사 주식에 대한 투자 관심이 높아질 수 있음을 의미한다."
    },
    {
      "source": "한국경제",
      "category": "국내",
      "title": "블랙록, 나스닥100 ETF 출시…年 0.12% 보수로 QQQ에 도전장",
      "link": "https://www.hankyung.com/article/202607082871i",
      "summary": "[배경/맥락] 블랙록이 나스닥100 지수를 추적하는 ETF를 연 0.12% 보수로 출시하며 기존 QQQ의 시장 점유율에 도전하고 있습니다. [투자 시사점] 투자자들은 더 낮은 수수료로 나스닥100 기술주 노출을 얻을 수 있는 선택지가 늘어났으므로, 기존 ETF 보유자들은"
    },
    {
      "source": "한국경제",
      "category": "국내",
      "title": "AI 반도체 최대 난제는 '열'…정부가 꺼내든 꿈의 소재",
      "link": "https://www.hankyung.com/article/202607082999i",
      "summary": "[배경/맥락] AI 반도체의 고발열 문제 해결을 위해 정부가 새로운 소재 개발에 나서고 있다. [투자 시사점] 반도체 냉각 소재 기술 개발 성공 시 AI칩 성능 향상과 관련 산업의 경쟁력 강화로 이어질 수 있어 주목할 필요가 있다."
    },
    {
      "source": "한국경제",
      "category": "국내",
      "title": "中 대표 자율주행 기업 모멘타, 홍콩 증시에 상장",
      "link": "https://www.hankyung.com/article/202607082956i",
      "summary": "[배경/맥락] 중국의 자율주행 기술 선도 기업인 모멘타가 홍콩 증시에 상장함으로써 글로벌 자본시장에서 중국 자율주행 산업의 성장성을 인정받았습니다.\n\n[투자 시사점] 이는 자율주행 기술 개발 경쟁이 심화되는 가운데 중국 기업의 기술력과 시장 영향력이 확대되고"
    },
    {
      "source": "한국경제",
      "category": "국내",
      "title": "'등급 인플레'에 칼 빼든 中…신용 거품 터진다 [차이나 워치]",
      "link": "https://www.hankyung.com/article/202607082953i",
      "summary": "**[배경/맥락]** 중국이 신용등급 부풀리기(등급 인플레)에 대한 규제를 강화하고 있으며, 이는 과도하게 높아진 신용등급이 실제 신용 위험을 제대로 반영하지 못하고 있음을 시사한다.\n\n**[투자 시사점]** 중국 채권 및 금융시장에서 신용등급 조정이 본격화될 경우 등급 하"
    },
    {
      "source": "연합뉴스",
      "category": "국내",
      "title": "코트라, 몽골서 CIS 무역투자 전략회의…수출 확대 지원",
      "link": "https://www.yna.co.kr/view/AKR20260708107400003",
      "summary": "[배경/맥락] 코트라가 몽골에서 CIS(독립국가연합) 지역을 대상으로 한 무역투자 전략회의를 개최하여 한국 기업들의 수출 확대를 지원하고 있다.\n\n[투자 시사점] 이는 몽골을 거점으로 중앙아시아 등 CIS 지역으로의 진출을 모색하는 기업들에게 공식적인 지원 채널이 마"
    },
    {
      "source": "연합뉴스",
      "category": "국내",
      "title": "코스닥, 10개월 만에 800선도 이탈…거래대금 7조원 아래로 '뚝'",
      "link": "https://www.yna.co.kr/view/AKR20260708113600008",
      "summary": "[배경/맥락] 코스닥이 10개월 만에 800선 아래로 내려갔으며, 일일 거래대금도 7조원 이하로 감소했다.\n\n[투자 시사점] 코스닥 지수 약세와 거래량 부진은 시장 심리 악화와 유동성 부족을 의미하므로, 투자자들은 변동성 확대에 대비하고 포지션 관리를 강화할 필요가 있"
    },
    {
      "source": "연합뉴스",
      "category": "국내",
      "title": "미래에셋, 개인투자용 국채 7월 청약…\"상반기 경쟁률 1.83대 1\"",
      "link": "https://www.yna.co.kr/view/AKR20260708113700008",
      "summary": "[배경/맥락] 미래에셋이 개인투자자를 대상으로 7월에 국채 청약을 실시하며, 상반기 국채 청약의 경쟁률이 1.83대 1로 나타났다.\n\n[투자 시사점] 국채에 대한 개인투자자의 수요가 지속적으로 존재하고 있어 안정적인 수익 창출 수단으로 국채가 주목받고 있음을 시사한"
    },
    {
      "source": "연합뉴스",
      "category": "국내",
      "title": "'임금님표 이천쌀' 미국에 20t 수출…호주 이어 올해 두번째",
      "link": "https://www.yna.co.kr/view/AKR20260708112700061",
      "summary": "[배경/맥락] 한국의 고급 쌀인 이천쌀이 미국으로 20톤 수출되었으며, 이는 호주에 이어 올해 두 번째 수출 사례입니다.\n\n[투자 시사점] 국내 농산물의 프리미엄 브랜드가 주요 선진국 시장 진출을 확대하고 있어 농식품 수출 기업의 성장성을 주목할 필요가 있습"
    }
  ],
  "portfolio": {
    "holdings": [
      {
        "시장": "국내",
        "종목명": "SK하이닉스",
        "섹터": "반도체",
        "코드": "000660",
        "보유량": "14",
        "매수평단가": "1,355,857.14",
        "매수총액($)": "18,982,000.00",
        "매수평단가(원)": "1,355,857",
        "매수총액(원)": "18,982,000",
        "평균환율": "1.00",
        "현재가": "₩",
        "": "(-4.59%)",
        "평가총액": "₩",
        "평가총액(원)": "₩ 29,400,000",
        "총수익": "₩",
        "원화수익": "₩ 10,418,000",
        "일간수익": "▼101,000.00"
      },
      {
        "시장": "국내",
        "종목명": "삼성전자",
        "섹터": "반도체",
        "코드": "005930",
        "보유량": "40",
        "매수평단가": "212,111.88",
        "매수총액($)": "8,484,475.00",
        "매수평단가(원)": "212,112",
        "매수총액(원)": "8,484,475",
        "평균환율": "1.00",
        "현재가": "₩",
        "": "(-6.93%)",
        "평가총액": "₩",
        "평가총액(원)": "₩ 11,040,000",
        "총수익": "₩",
        "원화수익": "₩ 2,555,525",
        "일간수익": "▼20,500.00"
      },
      {
        "시장": "미국",
        "종목명": "브로드컴",
        "섹터": "반도체",
        "코드": "AVGO",
        "보유량": "18",
        "매수평단가": "195.34",
        "매수총액($)": "3,516.10",
        "매수평단가(원)": "294,377",
        "매수총액(원)": "5,298,781",
        "평균환율": "",
        "현재가": "$",
        "": "(-0.83%)",
        "평가총액": "$",
        "평가총액(원)": "₩ 10,057,812",
        "총수익": "$",
        "원화수익": "₩ 4,759,031",
        "일간수익": "▼3.12"
      },
      {
        "시장": "국내",
        "종목명": "삼성전기",
        "섹터": "전기/전자",
        "코드": "009150",
        "보유량": "5",
        "매수평단가": "896,000.00",
        "매수총액($)": "4,480,000.00",
        "매수평단가(원)": "896,000",
        "매수총액(원)": "4,480,000",
        "평균환율": "1.00",
        "현재가": "₩",
        "": "(-10.44%)",
        "평가총액": "₩",
        "평가총액(원)": "₩ 7,375,000",
        "총수익": "₩",
        "원화수익": "₩ 2,895,000",
        "일간수익": "▼172,000.00"
      },
      {
        "시장": "미국",
        "종목명": "애플",
        "섹터": "기술주",
        "코드": "AAPL",
        "보유량": "15",
        "매수평단가": "218.31",
        "매수총액($)": "3,274.61",
        "매수평단가(원)": "328,990",
        "매수총액(원)": "4,934,854",
        "평균환율": "",
        "현재가": "$",
        "": "(-0.64%)",
        "평가총액": "$",
        "평가총액(원)": "₩ 7,022,493",
        "총수익": "$",
        "원화수익": "₩ 2,087,639",
        "일간수익": "▼2.00"
      },
      {
        "시장": "미국",
        "종목명": "엔비디아",
        "섹터": "반도체",
        "코드": "NVDA",
        "보유량": "20",
        "매수평단가": "129.31",
        "매수총액($)": "2,586.20",
        "매수평단가(원)": "194,871",
        "매수총액(원)": "3,897,416",
        "평균환율": "",
        "현재가": "$",
        "": "(+0.71%)",
        "평가총액": "$",
        "평가총액(원)": "₩ 5,935,490",
        "총수익": "$",
        "원화수익": "₩ 2,038,074",
        "일간수익": "▲1.38"
      },
      {
        "시장": "미국",
        "종목명": "마이크로소프트",
        "섹터": "클라우드",
        "코드": "MSFT",
        "보유량": "10",
        "매수평단가": "430.11",
        "매수총액($)": "4,301.15",
        "매수평단가(원)": "648,185",
        "매수총액(원)": "6,481,848",
        "평균환율": "",
        "현재가": "$",
        "": "(+0.54%)",
        "평가총액": "$",
        "평가총액(원)": "₩ 5,859,838",
        "총수익": "$",
        "원화수익": "₩ -622,010",
        "일간수익": "▲2.10"
      },
      {
        "시장": "국내",
        "종목명": "한국전력",
        "섹터": "전력",
        "코드": "015760",
        "보유량": "150",
        "매수평단가": "19,276.67",
        "매수총액($)": "2,891,500.00",
        "매수평단가(원)": "19,277",
        "매수총액(원)": "2,891,500",
        "평균환율": "1.00",
        "현재가": "₩",
        "": "(-4.84%)",
        "평가총액": "₩",
        "평가총액(원)": "₩ 5,452,500",
        "총수익": "₩",
        "원화수익": "₩ 2,561,000",
        "일간수익": "▼1,850.00"
      },
      {
        "시장": "미국",
        "종목명": "테슬라",
        "섹터": "자동차",
        "코드": "TSLA",
        "보유량": "7",
        "매수평단가": "428.74",
        "매수총액($)": "3,001.21",
        "매수평단가(원)": "646,120",
        "매수총액(원)": "4,522,838",
        "평균환율": "",
        "현재가": "$",
        "": "(-4.02%)",
        "평가총액": "$",
        "평가총액(원)": "₩ 4,250,206",
        "총수익": "$",
        "원화수익": "₩ -272,632",
        "일간수익": "▼16.87"
      },
      {
        "시장": "미국",
        "종목명": "TSMC",
        "섹터": "반도체",
        "코드": "TSM",
        "보유량": "4",
        "매수평단가": "185.03",
        "매수총액($)": "740.13",
        "매수평단가(원)": "278,844",
        "매수총액(원)": "1,115,377",
        "평균환율": "",
        "현재가": "$",
        "": "(-4.25%)",
        "평가총액": "$",
        "평가총액(원)": "₩ 2,607,541",
        "총수익": "$",
        "원화수익": "₩ 1,492,164",
        "일간수익": "▼19.22"
      },
      {
        "시장": "미국",
        "종목명": "IVV_S&P500",
        "섹터": "S&P500",
        "코드": "IVV",
        "보유량": "2",
        "매수평단가": "599.00",
        "매수총액($)": "1,198.00",
        "매수평단가(원)": "902,696",
        "매수총액(원)": "1,805,392",
        "평균환율": "",
        "현재가": "$",
        "": "(-0.49%)",
        "평가총액": "$",
        "평가총액(원)": "₩ 2,263,763",
        "총수익": "$",
        "원화수익": "₩ 458,371",
        "일간수익": "▼3.68"
      },
      {
        "시장": "국내",
        "종목명": "네이버",
        "섹터": "기술주",
        "코드": "035420",
        "보유량": "7",
        "매수평단가": "189,500.00",
        "매수총액($)": "1,326,500.00",
        "매수평단가(원)": "189,500",
        "매수총액(원)": "1,326,500",
        "평균환율": "1.00",
        "현재가": "₩",
        "": "(-3.04%)",
        "평가총액": "₩",
        "평가총액(원)": "₩ 1,338,400",
        "총수익": "₩",
        "원화수익": "₩ 11,900",
        "일간수익": "▼6,000.00"
      },
      {
        "시장": "미국",
        "종목명": "코카콜라",
        "섹터": "음료",
        "코드": "KO",
        "보유량": "10",
        "매수평단가": "65.36",
        "매수총액($)": "653.60",
        "매수평단가(원)": "98,498",
        "매수총액(원)": "984,978",
        "평균환율": "",
        "현재가": "$",
        "": "(+1.31%)",
        "평가총액": "$",
        "평가총액(원)": "₩ 1,266,638",
        "총수익": "$",
        "원화수익": "₩ 281,659",
        "일간수익": "▲1.09"
      },
      {
        "시장": "국내",
        "종목명": "현대차",
        "섹터": "자동차",
        "코드": "005380",
        "보유량": "2",
        "매수평단가": "274,500.00",
        "매수총액($)": "549,000.00",
        "매수평단가(원)": "274,500",
        "매수총액(원)": "549,000",
        "평균환율": "1.00",
        "현재가": "₩",
        "": "(-4.69%)",
        "평가총액": "₩",
        "평가총액(원)": "₩ 914,000",
        "총수익": "₩",
        "원화수익": "₩ 365,000",
        "일간수익": "▼22,500.00"
      },
      {
        "시장": "미국",
        "종목명": "월마트",
        "섹터": "도소매",
        "코드": "WMT",
        "보유량": "2",
        "매수평단가": "93.79",
        "매수총액($)": "187.58",
        "매수평단가(원)": "141,342",
        "매수총액(원)": "282,684",
        "평균환율": "",
        "현재가": "$",
        "": "(+0.80%)",
        "평가총액": "$",
        "평가총액(원)": "₩ 336,183",
        "총수익": "$",
        "원화수익": "₩ 53,499",
        "일간수익": "▲0.89"
      },
      {
        "시장": "미국",
        "종목명": "NVDL",
        "섹터": "반도체",
        "코드": "NVDL",
        "보유량": "6",
        "매수평단가": "66.16",
        "매수총액($)": "396.97",
        "매수평단가(원)": "99,706",
        "매수총액(원)": "598,234",
        "평균환율": "",
        "현재가": "$",
        "": "(+1.33%)",
        "평가총액": "$",
        "평가총액(원)": "₩ 261,405",
        "총수익": "$",
        "원화수익": "₩ -336,829",
        "일간수익": "▲0.38"
      }
    ],
    "count": 16
  },
  "ai": {
    "summary": "코스피 **-4.9%**(7281.1), 코스닥 **-5.18%**(788.14)로 국내 증시가 급락하며 대형주 전반에 매물 폭탄이 쏟아졌다. 원/달러 환율은 **1506.68원**으로 전일 대비 -1.44% 하락(원화 강세 전환)했으나 주가 낙폭을 방어하지 못했다.",
    "kr": "한국 시장 분석:\n1. **코스피 7281.1(-4.9%)**, **코스닥 788.14(-5.18%)** 로 양 지수 모두 5% 내외의 급락세를 기록했다. 단순 조정이 아닌 외국인·기관 동반 매도 압력이 작용한 것으로 추정된다.\n2. **원/달러 환율 1506.68원(-1.44%)** 으로 원화가 강세 전환됐음에도 주가 하락을 막지 못했다. 통상 원화 강세는 외국인 자금 유입 유인이 되지만, 오늘은 글로벌 리스크 오프 심리가 우세했던 것으로 판단된다.\n3. **삼성전자 278,750원(-5.83%)**, **SK하이닉스 2,105,000원(-4.36%)**, **한화 1,026,000원(-8.56%)**, **삼성바이오로직스 1,370,000원(-3.66%)**, **셀트리온 177,200원(-0.56%)** 으로 방산·반도체·바이오 전 섹터가 하락했다. 특히 **한화**의 낙폭이 -8.56%로 가장 심각하다.\n4. 대형주 전반의 5~8% 급락은 외국인의 대규모 순매도를 강하게 시사하며, 기관도 손절 매물을 내놓은 것으로 추정된다. 개인 투자자는 저가 매수 시도 여부가 오후 수급의 관건이다.\n5. 오늘 주목할 포인트는 **코스피 7,281선 지지 여부**와 장 마감 후 외국인 순매수·순매도 집계다. 추가 하락 시 7,000선 지지 여부를 중기 관전 포인트로 삼아야 한다.",
    "us": "미국 시장 분석:\n1. **다우 52,925(-0.25%)**, **S&P500 7,503.85(-0.45%)**, **나스닥 25,818.69(-1.16%)** 로 미국 지수는 소폭 하락에 그쳤다. 국내 급락과 달리 미국은 상대적으로 안정적인 흐름을 유지했다.\n2. 나스닥 내 빅테크 종목은 혼조세를 보였다. **Meta +2.55%(615.58달러)**, **MSFT +0.54%(388.84달러)**, **NVDA +0.71%(196.93달러)** 는 상승한 반면, **TSLA -4.02%(402.9달러)**, **AAPL -0.64%(310.66달러)** 는 하락했다.\n3. **미국 10년물 금리 4.529%(+0.98%)**, **30년물 5.043%(+1.16%)** 로 장기 금리가 모두 상승했다. 장기채 금리 상승은 성장주 밸류에이션 압박 요인이며 글로벌 자금의 위험자산 이탈을 자극할 수 있다.\n4. **달러 인덱스(DXY) 101.051(-0.09%)** 로 달러는 소폭 약세였다. 달러 약세는 신흥국 통화 및 원화 강세를 뒷받침하지만, 오늘 한국 시장에는 실질적 방어 효과가 없었다.\n5. 미국 시장의 낙폭이 제한적(-0.45% 수준)이었음에도 국내 시장이 5% 가까이 급락한 것은 한국 고유의 수급 불안 또는 특정 이벤트성 충격이 반영된 것으로 보이며, 미국 장 추가 하락 여부가 내일 국내 시장 방향을 결정할 핵심 변수다.",
    "sectors": "상승 섹터:\n1. 에너지/정유 - **WTI 72.75달러(+3.28%)**, **브렌트 76.57달러(+3.25%)** 로 유가가 3% 이상 급등해 정유·에너지 섹터 수혜가 기대된다.\n2. 소셜미디어/광고 플랫폼 - **Meta +2.55%** 로 광고 기반 플랫폼 기업이 강세를 보이며 해당 섹터의 상대적 강도가 확인됐다.\n3. 귀금속/은 - **은(Silver) 61.31달러(+0.62%)** 로 소폭 상승하며 안전자산 및 산업용 귀금속 수요가 유지되고 있다.\n하락/주의 섹터:\n1. 반도체 - **삼성전자 -5.83%**, **SK하이닉스 -4.36%** 로 국내 대표 반도체 종목이 동반 급락했다. 미국채 금리 상승에 따른 성장주 할인율 확대가 반도체 고밸류에이션 부담을 키웠다.\n2. 방산 - **한화 -8.56%** 로 단일 종목 기준 가장 큰 낙폭을 기록했다. 차익실현 매물 또는 섹터 순환 매도가 집중된 것으로 보인다.\n3. 바이오/제약 - **삼성바이오로직스 -3.66%**, **셀트리온 -0.56%** 로 하락했다. 셀트리온의 낙폭은 상대적으로 작았으나 전반적 바이오 투자심리는 냉각됐다.\n중립 관망:\n1. 금(Gold) - **4139.9달러(-0.13%)** 로 보합 수준을 유지해 안전자산 매수세와 차익실현이 균형을 이루고 있다.\n2. 빅테크 소프트웨어 - **MSFT +0.54%**, **GOOGL +0.16%** 로 미세한 플러스를 기록했으나 방향성이 뚜렷하지 않아 관망이 적절하다.",
    "holdings": "내 보유종목 액션:\n1. **SK하이닉스 2,105,000원(-4.36%)** - 하루 만에 4% 이상 하락한 상황으로 추가 손절보다는 현 포지션 유지 후 지지선 확인이 우선이다. 반도체 업황 전반의 방향성이 확인될 때까지 신규 매수 자제를 권장한다.\n2. **삼성전자 278,750원(-5.83%)** - 5% 이상의 급락으로 단기 낙폭이 과도하나, 추가 하락 리스크도 배제할 수 없다. 지지선 이탈 여부를 확인하며 분할 손절 또는 홀딩 전략을 병행 검토해야 한다.",
    "picks": "관심 분야 (데이터 기반):\n1. **에너지/정유 섹터**: WTI +3.28%, 브렌트 +3.25%로 유가가 강하게 반등하고 있어 정유·에너지 관련 종목의 단기 모멘텀이 살아있다.\n2. **Meta(소셜미디어 광고)**: **Meta +2.55%(615.58달러)** 로 지수 대비 강한 상승을 기록했다. 광고 수요 회복 기대감이 반영된 것으로 보여 지속 모니터링 가치가 있다.\n3. **NVDA(AI 반도체)**: **NVDA +0.71%(196.93달러)** 로 국내 반도체 급락 속에서도 미국 AI 반도체는 플러스를 유지했다. 국내외 반도체 디커플링 여부를 주목할 필요가 있다.\n4. **귀금속(은/골드)**: **금 4139.9달러(-0.13%)**, **은 61.31달러(+0.62%)** 로 시장 변동성 확대 국면에서 귀금속이 상대적 안전자산 역할을 수행하고 있어 헤지 수단으로 관심을 가질 만하다.",
    "do": "오늘 할 것:\n1. **보유 16개 종목 전체 손익 현황 점검** - 오늘처럼 시장 전반이 5% 급락하는 날은 포트폴리오 내 종목별 낙폭 차이를 확인해 상대 강도가 낮은 종목부터 우선 정리 여부를 판단해야 한다.\n2. **SK하이닉스·삼성전자의 단기 지지선 설정** - 현재 각각 2,105,000원, 278,750원 수준에서 추가 하락 시 손절 또는 분할 매수 기준선을 명확히 정해두어야 한다.\n3. **미국 장기금리(10년물 4.529%, 30년물 5.043%) 추이 모니터링** - 금리가 추가 상승하면 성장주·반도체 추가 하락 압력이 커지므로 장중 금리 변동을 지속 확인한다.\n4. **유가 상승(WTI +3.28%) 수혜 섹터 탐색** - 에너지 관련 섹터는 오늘 유일하게 강세를 보인 분야이므로, 관련 종목 편입 검토를 위한 사전 리서치를 진행한다.",
    "dont": "오늘 하지 말 것:\n1. **급락 속 충동적 반도체 추가 매수 금지** - 삼성전자(-5.83%), SK하이닉스(-4.36%)가 급락했다고 해서 바닥 확인 없이 즉각 추가 매수하면 추가 하락 시 손실이 더 커질 수 있다.\n2. **한화(-8.56%) 등 낙폭 과대 종목 무분별 저가 매수 금지** - 단일 종목이 하루 8% 이상 하락한 경우 구조적 매도 이슈가 있을 수 있으므로, 원인이 확인되기 전까지 진입을 자제한다.\n3. **16개 종목 포트폴리오에서 신규 종목 무리하게 추가 금지** - 현재 보유 종목 수가 이미 16개로 분산이 충분한 상태에서 급락장에 추가 편입하면 리스크 관리가 어려워진다.\n4. **단기 반등 기대로 레버리지 또는 집중 투자 금지** - 코스피·코스닥 모두 5% 내외 급락한 날 장 마감 전후 단기 반등을 노린 고위험 매매는 추가 하락 리스크를 감안할 때 절대 피해야 한다.",
    "risk_level": 5
  },
  "youtube": [
    {
      "name": "한국경제TV",
      "type": "media",
      "videoId": "NTvnrZNyLZU",
      "title": "흔들리는 투심…코스피, 전날 급락딛고 반등시도하나 #코스피전망  #삼성전자",
      "updated": "2026-07-07T22:52:34+00:00",
      "summary": "**핵심 주제:**\n전날 급락한 코스피가 반등을 시도하면서 시장 심리가 불안정한 상황\n\n**주목 키워드:**\n- 코스피\n- 급락\n- 반등\n- 투심 흔들림\n- 삼성전자",
      "isNew": true
    },
    {
      "name": "한국경제TV",
      "type": "media",
      "videoId": "byR3mNzyhhE",
      "title": "7월 8일 글로벌 1분 시황✅ #당잠사 #굿모닝한경글로벌마켓 #1분시황",
      "updated": "2026-07-07T23:02:14+00:00",
      "summary": "[ 핵심 메시지 ]\n\n- 삼성전자 호실적에도 불구하고 높아진 시장 기대치로 인한 주가 급락으로 실적과 주가의 괴리 심화\n- 중국 딥시크의 AI 칩 자체 개발과 스페이스X 신규 AI 모델 출시 임박으로 AI 칩 시장 경쟁 심화\n- 중동 긴장 고조로 유가 급등 및 금리 상승으로 인한 글로벌 시장 불안 확대\n\n[ 주목 섹터/종목 ]\n\n- 에너지/유가 - 호르무즈 해협 유조선 피격 및 미국의 이란 공습으로 WTI 5% 이상 급등하며 상승 모멘텀 강화\n- AI 칩 - 딥시크 자체 칩 개발과 스페이스X AI 모델 출시로 엔비디아 독점 구도 약화, 인텔/AMD 등 경쟁 심화\n- 메타/아마존 - 자체 AI 솔루션 개발로 AI 투자 효율화 추진 중이며 긍정적 반응\n\n[ 매수 시그널 ]\n\n- 에너지 관련 종목은 중동 긴장 지속 시 추가 상승 가능성\n- 메타의 이미지 생성 모델 출시 등 자체 AI 개발 진전 시 매수 기회\n- 삼성전자 같은 실적 우량주는 시장 기대치 조정 후 저점 매수 타이밍 주시\n\n[ 매도/주의 ]\n\n- 중동 분쟁 확대 시 유가 급등으로 인한 인플레이션 재점화 우려\n- AI 칩 시장 경쟁 심화로 엔비디아 등 기존 강자의 마진율 압박 가능성\n- 금리 상승 추세 지속 시 성장주 밸류에이션 하락 압력 증가\n- 스페이스X 신규 상장 초기 변동성 높음\n\n[ 오늘 액션 ]\n\n- 에너지 관련 ETF 또는 석유 관련 종목 포지션 검토\n- AI 칩 관련 종목 중 엔비디아 외 대체 기업 분석 필요\n- 중동 뉴스 모니터링으로 유가 추가 상승 시나리오 대비\n- 금리 상승에 따른 포트폴리오 듀레이션 조정 검토",
      "isNew": true
    },
    {
      "name": "한국경제TV",
      "type": "media",
      "videoId": "ZJexU9EHn98",
      "title": "삼성전자 쇼크! 5년 전 아마존 쇼크된다고? | No! 삼전닉스 레버리지가 문제, 이런 대책을? | 한상춘 한국경제신문 논설위원",
      "updated": "2026-07-07T23:00:19+00:00",
      "summary": "# 핵심 주제\n삼성전자의 현재 위기가 5년 전 아마존과 다른 이유는 레버리지(차입금) 문제에 있으며, 이에 대한 대책이 필요하다는 분석\n\n# 주목 키워드\n- 삼성전자 쇼크\n- 아마존 쇼크 (5년 전)\n- 레버리지 (차입금)\n- 대책",
      "isNew": true
    },
    {
      "name": "한국경제TV",
      "type": "media",
      "videoId": "ENrl6p5N1uM",
      "title": "“메모리 겨울 온다”던 모건스탠리, 반도체 여력 다했나… #삼성전자 #어닝서프라이즈 #반도체전망",
      "updated": "2026-07-07T22:51:33+00:00",
      "summary": "# 핵심 주제\n모건스탠리가 예측한 메모리 반도체 약세 전망이 실현되지 않으면서 삼성전자의 어닝 서프라이즈 가능성과 반도체 산업 전망의 불확실성이 대두되고 있다.\n\n# 주목 키워드\n- 메모리 반도체 약세 전망 (모건스탠리)\n- 어닝 서프라이즈 (삼성전자)\n- 반도체 여력/공급 상황\n- 반도체 산업 전망 재평가",
      "isNew": true
    },
    {
      "name": "한국경제TV",
      "type": "media",
      "videoId": "RGfuDk3y5Xw",
      "title": "반도체주 급락·유가 급등... 뉴욕증시 하락 마감ㅣ 뉴욕인사이트_김선형 ㅣ260708",
      "updated": "2026-07-07T22:34:27+00:00",
      "summary": "# 핵심 주제\n반도체주 급락과 유가 급등으로 뉴욕증시가 하락 마감했으며, 이는 투자자들의 포트폴리오 재조정이 필요한 상황을 의미한다.\n\n# 주목 키워드\n- 반도체주 급락\n- 유가 급등\n- 뉴욕증시 하락\n- 포트폴리오 리스크",
      "isNew": true
    },
    {
      "name": "한국경제TV",
      "type": "media",
      "videoId": "DSSwYT3cfnA",
      "title": "[🔴07/08 #당잠사]이란, 호르무즈 유조선 공격…국제유가 상승ㅣ삼성전자 호실적에도 하락…미국 반도체 ‘흔들’ㅣ스페이스X 나스닥 100 편입ㅣ#아마존 #스페이스X #마이크로소프트",
      "updated": "2026-07-07T21:19:29+00:00",
      "summary": "[ 핵심 메시지 ]\n\n- 반도체 후기 사이클 진입 우려로 인한 광범위한 기술주 조정 국면\n- 중동 긴장 고조와 인플레이션 재부상으로 인한 경제 불확실성 증대\n- 대형 기술기업들의 AI 투자 수익성 확보 여부가 향후 시장 방향성 결정\n\n[ 주목 섹터/종목 ]\n\n- 방어주 및 헬스케어 - 위험자산 회피 심리로 자금 이동 중이며 UnitedHealth가 사상 최고치 경신\n- 에너지주 - 중동 긴장으로 유가 급등하며 Exxon Mobil 3.85% 상승\n- 소비재 대형주 - Walmart의 가격 인하 전략으로 소비심리 방어 중\n\n[ 매수 시그널 ]\n\n- 7월 하순 하이퍼스케일러 실적 발표 이후 반도체주 변동성 수렴 시점\n- 중동 긴장 완화 신호 시 기술주 매수 기회\n- 대형 클라우드 기업들의 AI 투자 수익성 확인 후 반도체주 재평가\n\n[ 매도/주의 ]\n\n- 반도체 공급 증가로 인한 가격 하락 리스크\n- 중국 딥시크의 자체 AI칩 개발로 엔비디아 의존도 감소 가능성\n- 중동 지역 유조선 공격으로 인한 유가 급등과 인플레이션 재부상\n- 인텔 2분기 실적 발표 전 관망 심리로 인한 추가 하락 가능성\n- 기술주 광범위한 조정 속 개별 종목 선별 필요\n\n[ 오늘 액션 ]\n\n- 반도체주 매수는 보류하고 7월 하순 실적 발표 결과 확인 후 진행\n- 방어주와 에너지주로 포트폴리오 방어 강화\n- 중동 긴장 상황 모니터링으로 유가 및 금리 변동성 대비\n- 대형 기술기업의 AI 수익성 개선 전략 추적 관찰",
      "isNew": true
    },
    {
      "name": "한국경제TV",
      "type": "media",
      "videoId": "1KEYuLAxJ4A",
      "title": "삼성전자 역대급 실적 폭발에도 터진 서킷브레이커, 호재의 역설과 셀온 쇼크… 뷰티 반도체 화장품의 구원 vs 삼전닉스 전방위 급락 l 허반석·김정기·박우신·황유현 l 더 워룸 2부",
      "updated": "2026-07-07T15:52:58+00:00",
      "summary": "# 핵심 주제\n삼성전자의 역대급 실적에도 불구하고 주가가 급락하는 역설적 현상과 이에 따른 투자 시사점을 분석하는 내용\n\n# 주목 키워드\n- 서킷브레이커 (주가 급락)\n- 호재의 역설 (좋은 실적 vs 주가 하락)\n- 셀온 쇼크\n- 뷰티 반도체\n- 삼전닉스 (삼성전자 약세)",
      "isNew": true
    },
    {
      "name": "연합뉴스경제TV",
      "type": "media",
      "videoId": "zbw7eywXvnE",
      "title": "그린란드 또 소환한 트럼프 \"우리가 통제해야\"…덴마크 반발",
      "updated": "2026-07-07T23:16:04+00:00",
      "summary": "# 핵심 주제\n트럼프 전 대통령이 그린란드의 미국 통제를 주장하며 덴마크와의 영토 분쟁이 심화되고 있습니다.\n\n# 주목 키워드\n- 그린란드\n- 트럼프\n- 영토 통제권\n- 덴마크 반발\n- 지정학적 갈등",
      "isNew": true
    },
    {
      "name": "연합뉴스경제TV",
      "type": "media",
      "videoId": "LQs2vNjyfgA",
      "title": "미국 정부, 한국 조선사에 전투함·급유함 타진…첫 정보요청",
      "updated": "2026-07-07T22:56:50+00:00",
      "summary": "# 핵심 주제\n미국 정부가 한국 조선사에 전투함과 급유함 건조를 처음으로 공식 문의하면서 한국 방위산업의 수출 기회가 확대되고 있다.\n\n# 주목 키워드\n- 미국 정부 수요\n- 한국 조선사\n- 전투함·급유함\n- 첫 정보요청\n- 방위산업 수출",
      "isNew": true
    },
    {
      "name": "연합뉴스경제TV",
      "type": "media",
      "videoId": "Ua4mRLQN3Q0",
      "title": "韓-나토, 조달기본협정 추진…\"年 15조원 방산시장 진출 발판\"",
      "updated": "2026-07-07T22:51:03+00:00",
      "summary": "# 핵심 주제\n한국이 나토와 조달기본협정을 추진하여 연 15조원 규모의 방산시장 진출 기회를 확보하려는 움직임\n\n# 주목 키워드\n- 한-나토 조달기본협정\n- 방산시장 진출\n- 연 15조원 규모\n- 수출 기회 확대",
      "isNew": true
    },
    {
      "name": "연합뉴스경제TV",
      "type": "media",
      "videoId": "94ojAb8Lsbk",
      "title": "야놀자, 기업공개 '좌초 위기'…해외 투자유치 담당 임원 줄퇴사",
      "updated": "2026-07-07T22:46:45+00:00",
      "summary": "# 핵심 주제\n야놀자의 기업공개(IPO) 추진이 어려움에 직면한 가운데 해외 투자유치 담당 임원들의 집단 퇴사가 발생했다.\n\n# 주목 키워드\n- 야놀자\n- 기업공개(IPO)\n- 좌초 위기\n- 해외 투자유치\n- 임원 줄퇴사",
      "isNew": true
    },
    {
      "name": "연합뉴스경제TV",
      "type": "media",
      "videoId": "ur7y6sfPOlc",
      "title": "🔴[생방송] \"삼전닉스 이젠 팔아라\" 경고 | 반도체 실적 발표 후 대응은?  |  마켓포커스 260708",
      "updated": "2026-07-07T22:43:12+00:00",
      "summary": "# 핵심 주제\n삼성전자와 SK하이닉스 반도체 기업들의 실적 발표 이후 주가 대응 방향에 대한 투자 판단 정보를 제공하는 콘텐츠입니다.\n\n# 주목 키워드\n- 삼성전자, SK하이닉스\n- 반도체 실적 발표\n- 매도 신호 (\"팔아라\" 경고)\n- 주가 대응 전략",
      "isNew": true
    },
    {
      "name": "연합뉴스경제TV",
      "type": "media",
      "videoId": "wxhbtPdLBsM",
      "title": "아마존 또 회사채 38조원 발행…대부분 AI 인프라 투자할듯",
      "updated": "2026-07-07T22:06:56+00:00",
      "summary": "# 핵심 주제\n아마존이 38조원 규모의 회사채를 발행하여 AI 인프라 투자에 집중하고 있다.\n\n# 주목 키워드\n- 아마존\n- 회사채 발행 (38조원)\n- AI 인프라 투자",
      "isNew": true
    },
    {
      "name": "연합뉴스경제TV",
      "type": "media",
      "videoId": "a4CupULJTW4",
      "title": "\"中 딥시크, 자체 AI 칩 개발 중\"",
      "updated": "2026-07-07T21:44:33+00:00",
      "summary": "# 핵심 주제\n중국의 딥시크가 자체 AI 칩 개발을 추진하면서 글로벌 반도체 시장의 경쟁 구도가 재편될 가능성이 제기되고 있다.\n\n# 주목 키워드\n- 딥시크(DeepSeek)\n- 자체 AI 칩 개발\n- 중국\n- 반도체 자급화",
      "isNew": true
    },
    {
      "name": "연합뉴스경제TV",
      "type": "media",
      "videoId": "PfT70WSIDoQ",
      "title": "미군 \"호르무즈 상선 공격한 이란에 강력한 공습 개시\"",
      "updated": "2026-07-07T21:37:30+00:00",
      "summary": "# 핵심 주제\n미군이 호르무즈 해협 상선 공격에 대응하여 이란에 공습을 개시함에 따라 중동 지정학적 긴장이 고조되고 있습니다.\n\n# 주목 키워드\n- 호르무즈 해협 (글로벌 석유 공급로)\n- 이란-미국 군사 충돌\n- 유가 변동성 (에너지 가격 영향)\n- 지정학적 리스크",
      "isNew": true
    },
    {
      "name": "연합뉴스경제TV",
      "type": "media",
      "videoId": "uCiNdAvouSA",
      "title": "이란 \"일부 상선, 이란과 협의되지 않은 항로 이용\"…사실상 공격 인정",
      "updated": "2026-07-07T21:30:46+00:00",
      "summary": "# 핵심 주제\n이란이 상선 공격을 암시적으로 인정하면서 중동 지역 해상 안보 불안정이 심화되고 있다.\n\n# 주목 키워드\n- 이란 상선 공격\n- 중동 해상 안보\n- 지정학적 리스크\n- 해운·에너지 가격 변동성",
      "isNew": true
    },
    {
      "name": "연합뉴스경제TV",
      "type": "media",
      "videoId": "UMN2fyYuatE",
      "title": "삼성전자의 '왝더독'…뉴욕증시 동반 하락, 필리 4.6%↓",
      "updated": "2026-07-07T21:26:42+00:00",
      "summary": "# 핵심 주제\n삼성전자가 뉴욕증시 하락에 동반하여 주가가 하락했으며, 필라델피아 반도체지수가 4.6% 하락했다.\n\n# 주목 키워드\n- 삼성전자\n- 뉴욕증시 동반 하락\n- 필라델피아 반도체지수(필리) 4.6% 하락\n- 왝더독(Whack-a-Mole, 악재의 반복 발생)",
      "isNew": true
    },
    {
      "name": "연합뉴스경제TV",
      "type": "media",
      "videoId": "-kk7VBvusQc",
      "title": "\"SK하이닉스 ADR, 공모물량 대비 '몇배' 몰려…장기 투자자 강한 수요\"",
      "updated": "2026-07-07T21:17:51+00:00",
      "summary": "# 핵심 주제\nSK하이닉스의 ADR(미국예탁증권) 공모에서 공급량을 초과하는 수요가 몰리며 장기 투자자들의 강한 관심을 보이고 있다.\n\n# 주목 키워드\n- SK하이닉스 ADR\n- 공모물량 초과 수요\n- 장기 투자자 수요",
      "isNew": true
    },
    {
      "name": "매일경제TV",
      "type": "media",
      "videoId": "5_794z3QmBM",
      "title": "🔴삼성전자 목표주가 39만 원 vs 60만 원흔들림은 기회인가, 진짜 위기인가? l 매아리",
      "updated": "2026-07-07T22:16:21+00:00",
      "summary": "# 핵심 주제\n삼성전자의 목표주가 편차(39만 원 vs 60만 원)로 인한 시장 불확실성이 투자 기회인지 위험인지를 판단하는 것이 주요 관심사이다.\n\n# 주목 키워드\n- 삼성전자\n- 목표주가 (39만 원, 60만 원)\n- 변동성/흔들림\n- 기회 vs 위기",
      "isNew": true
    },
    {
      "name": "경제사냥꾼",
      "type": "yt",
      "videoId": "WqNUPopKWAw",
      "title": "모건스탠리가 삼전·닉스 역대급 하락장 올 수도 있다는 이유",
      "updated": "2026-07-07T23:00:36+00:00",
      "summary": "[ 핵심 요약 ]\n\n- 삼성전자 2분기 영업이익 89조 4천억으로 역대급 실적을 기록했으나 주가는 오히려 7% 하락한 것은 차익실현 매물 때문이지 실적 악화 때문이 아님\n\n- 모건 스탠리의 메모리 비중 축소 권고는 겨울이 온다는 뜻이 아니라 주도주가 반도체에서 데이터센터 기업으로 순환한다는 의미일 뿐 메모리 수요는 여전히 강함\n\n- 2019년 이후 삼성의 어닝 서프라이즈 16번 중 10번이 발표 직후 주가 하락했으며 이는 소문에 사서 뉴스에 파는 패턴의 반복\n\n[ 주요 내용 ]\n\n- 모건 스탠리는 내년 삼성 이익이 올해보다 35~40% 더 증가할 것으로 전망했으며 장기 전망은 긍정적으로 유지 중\n\n- 2024년 9월 SK하이닉스 목표가를 26만원에서 12만원으로 인하했던 모건 스탠리가 이후 110만원으로 상향 조정한 사례처럼 공포 장세에서 저평가 매수 기회 존재\n\n- 국내 증권가는 메모리 공급이 내년 4분기까지 수요를 못 따라가고 HBM 판매 단가가 91% 상승할 것으로 전망하며 삼성과 하이닉스의 PER이 글로벌 경쟁사 절반 수준으로 저평가 상태\n\n- 데이터센터 기업들도 결국 한국 메모리를 구매하는 큰 손이며 하이닉스의 나스닥 ADR 상장으로 글로벌 자금 유입 통로가 추가로 열릴 예정",
      "isNew": false
    },
    {
      "name": "경제사냥꾼",
      "type": "yt",
      "videoId": "LW6PEpEzreQ",
      "title": "투자자들이 꼭 알아야 하는 부동산vs한국주식vs미국주식 세금 계산 법",
      "updated": "2026-07-07T21:00:09+00:00",
      "summary": "[ 핵심 요약 ]\n\n- 동일한 1억 수익이라도 부동산, 한국 주식, 미국 주식에서 나오는 세금이 완전히 다르므로 손에 남는 금액이 크게 달라짐\n\n- 한국 주식은 양도소득세 없지만 매도 시 0.2% 거래세 부담, 미국 주식은 수익의 22% 세금(250만 원 공제 후), 부동산은 1세대 1주택 여부와 조정 대상 지역 등 자격에 따라 세금이 0원부터 중과세까지 차등 적용\n\n- 세금 구조는 단순 비용이 아니라 정부의 자산 시장 조절 수단이며, 고수 투자자들은 수익률보다 세금 확정 시점을 전략적으로 통제함\n\n[ 주요 내용 ]\n\n- 한국 주식은 소액 주주의 장내 거래 시 양도소득세가 없으나 매도 금액의 0.2% 거래세가 발생하며, 손절매 시에도 세금을 내야 함\n\n- 미국 주식은 1년 수익에서 250만 원을 공제한 후 남은 차익의 22%를 세금으로 납부하므로 1억 수익 시 약 2,145만 원의 세금 발생\n\n- 부동산은 1세대 1주tactics택 2년 이상 보유, 조정 대상 지역 거주 요건 충족, 12억 이하 판매 시 양도세 면제 가능하나 다주택자는 중과세 대상\n\n- 세금 확정을 늦출수록 미확정 세금까지 복리로 굴러가므로 세금 납부 시점 조절이 중요한 투자 전략이며, 국내 주식 손실은 미국 주식 이익과 상계 불가",
      "isNew": false
    },
    {
      "name": "경제사냥꾼",
      "type": "yt",
      "videoId": "vJcWncRmH8E",
      "title": "삼성전자 실적은 역대급인데, 주가는 '폭락하는' 진짜 이유",
      "updated": "2026-07-07T16:00:03+00:00",
      "summary": "[ 핵심 요약 ]\n\n- 삼성전자가 역대급 실적(영업이익 89조 4천억원, 전분기 대비 56% 증가)을 기록했음에도 주가가 7% 이상 하락한 이유는 외국인의 차익 실현 때문\n\n- 시장이 현재의 높은 이익이 AI 메모리 가격 상승에 의존하고 있으며, 가격 하락 시 이익이 급감할 수 있다고 우려\n\n- 회사의 영업이익과 주주에게 실제로 돌아오는 현금은 다르며, 성과급과 설비투자 등으로 인한 비용 발생을 고려해야 함\n\n[ 주요 내용 ]\n\n- 외국인이 삼성전자에서 600만주 이상 순매도하면서 개인투자자가 이를 받아내는 손바뀌 현상 발생\n\n- 현재 삼성전자의 높은 이익은 AI 수요로 인한 디램, 낸드, HBM 등 메모리 가격 폭등(한 분기 40~50% 상승)에 기인\n\n- 2018년 반도체 슈퍼사이클 이후 메모리 가격 하락으로 실적과 주가가 동반 하락한 역사적 선례 존재\n\n- 직원 성과급, 설비투자, 공장 증설 등으로 인해 발표된 영업이익이 모두 주주에게 돌아오지 않음을 의미",
      "isNew": false
    },
    {
      "name": "경제사냥꾼",
      "type": "yt",
      "videoId": "I6LIrJ68eBM",
      "title": "월가에서 ‘비트코인 반등장’ 올 수 있다는 진짜 이유",
      "updated": "2026-07-07T15:00:17+00:00",
      "summary": "[ 핵심 요약 ]\n\n- 월가는 현재 6만 달러대 비트코인이 연말 15만 달러까지 상승할 수 있다고 전망하며 규제 명확성과 기관 자금 유입을 핵심 요인으로 봄\n\n- 이번 하락장은 과거와 달리 거래소 파산이나 강제 청산 없이 기관 자금이 오히려 순유입되는 구조적 차이가 있음\n\n- 비트코인이 투기 자산에서 제도권 자산으로 재평가될 가능성이 높으며 트럼프의 정부 보유 비트코인 전략 비축 계획이 이를 뒷받침함\n\n[ 주요 내용 ]\n\n- 미국 비트코인 현물 ETF에 하루 2억 6,500만 달러 이상이 순유입되고 있으며 이는 제도권 자금의 재진입 신호를 의미함\n\n- 미국에서 비트코인을 증권 또는 상품으로 분류하는 규제 정리가 진행 중이며 규제 명확성이 확보되면 연기금과 대형 금융사의 포트폴리오 편입이 가능해짐\n\n- 마이클 세일러의 마이크로스트레티지가 비트코인 3,588개를 판 것은 강제 청산이 아닌 현금 유동성 조정으로 해석되며 여전히 84만 개 이상을 보유 중임\n\n- 향후 주목할 지표는 ETF 순유입의 지속성과 비트코인이 68,000달러 저항선을 돌파하는지 여부이며 두 조건이 충족되면 단순 반등이 아닌 추세 복귀로 판단 가능함",
      "isNew": false
    }
  ]
}