{
  "updated": "2026-06-24T23:34:51Z",
  "market": {
    "kospi": {
      "price": 8471.02,
      "change": -643.5298,
      "pct": -7.06,
      "high": 0.0,
      "low": 0.0,
      "vol": 0,
      "candles": [
        {
          "time": 1781740800,
          "open": 8884.9199,
          "high": 9106.0703,
          "low": 8867.3398,
          "close": 9063.8398,
          "vol": 510900
        },
        {
          "time": 1781827200,
          "open": 9288.8896,
          "high": 9385.5898,
          "low": 8831.7197,
          "close": 9052.4199,
          "vol": 517200
        },
        {
          "time": 1782086400,
          "open": 8954.4297,
          "high": 9253.0,
          "low": 8900.6797,
          "close": 9114.5498,
          "vol": 381100
        },
        {
          "time": 1782172800,
          "open": 9083.54,
          "high": 9175.4502,
          "low": 8203.8398,
          "close": 8203.8398,
          "vol": 488700
        }
      ]
    },
    "kosdaq": {
      "price": 909.31,
      "change": -59.09,
      "pct": -6.1,
      "high": 0.0,
      "low": 0.0,
      "vol": 0,
      "candles": [
        {
          "time": 1781740800,
          "open": 1029.8101,
          "high": 1031.54,
          "low": 996.93,
          "close": 1000.93,
          "vol": 611800
        },
        {
          "time": 1781827200,
          "open": 1001.4,
          "high": 1001.4,
          "low": 946.15,
          "close": 966.59,
          "vol": 882500
        },
        {
          "time": 1782086400,
          "open": 957.49,
          "high": 979.58,
          "low": 944.31,
          "close": 968.4,
          "vol": 631800
        },
        {
          "time": 1782172800,
          "open": 958.64,
          "high": 971.69,
          "low": 891.52,
          "close": 891.52,
          "vol": 797400
        }
      ]
    },
    "sp500": {
      "price": 7358.22,
      "change": -7.24,
      "pct": -0.1,
      "high": 7428.06,
      "low": 7336.82,
      "vol": 3600977000,
      "candles": [
        {
          "time": 1781703000,
          "open": 7524.5,
          "high": 7532.1699,
          "low": 7402.6099,
          "close": 7420.1001,
          "vol": 5883740000
        },
        {
          "time": 1781789400,
          "open": 7487.3599,
          "high": 7511.0698,
          "low": 7468.3198,
          "close": 7500.5801,
          "vol": 9061110000
        },
        {
          "time": 1782135000,
          "open": 7500.4399,
          "high": 7530.0098,
          "low": 7460.0098,
          "close": 7472.79,
          "vol": 5976740000
        },
        {
          "time": 1782221400,
          "open": 7366.5098,
          "high": 7424.1699,
          "low": 7347.6001,
          "close": 7365.46,
          "vol": 5640530000
        },
        {
          "time": 1782307800,
          "open": 7370.8799,
          "high": 7428.0601,
          "low": 7336.8198,
          "close": 7358.2202,
          "vol": 3600977000
        }
      ]
    },
    "nasdaq": {
      "price": 25476.635,
      "change": -110.4041,
      "pct": -0.43,
      "high": 25840.564,
      "low": 25354.656,
      "vol": 14182636000,
      "candles": [
        {
          "time": 1781703000,
          "open": 26493.8203,
          "high": 26511.5508,
          "low": 25960.4102,
          "close": 26021.6602,
          "vol": 11443600000
        },
        {
          "time": 1781789400,
          "open": 26410.6191,
          "high": 26559.7402,
          "low": 26188.6895,
          "close": 26517.9297,
          "vol": 18286150000
        },
        {
          "time": 1782135000,
          "open": 26483.3105,
          "high": 26561.1191,
          "low": 26125.4805,
          "close": 26166.5996,
          "vol": 12844290000
        },
        {
          "time": 1782221400,
          "open": 25549.7598,
          "high": 25882.5703,
          "low": 25513.2598,
          "close": 25587.0391,
          "vol": 14631520000
        },
        {
          "time": 1782307800,
          "open": 25578.623,
          "high": 25840.5645,
          "low": 25354.6562,
          "close": 25476.6348,
          "vol": 14182636000
        }
      ]
    },
    "dow": {
      "price": 51848.9,
      "change": 182.0602,
      "pct": 0.35,
      "high": 52248.69,
      "low": 51617.73,
      "vol": 560271694,
      "candles": [
        {
          "time": 1781703000,
          "open": 51937.5586,
          "high": 52281.1914,
          "low": 51392.5781,
          "close": 51492.5508,
          "vol": 496040000
        },
        {
          "time": 1781789400,
          "open": 51571.8516,
          "high": 51949.2617,
          "low": 51554.5312,
          "close": 51564.6992,
          "vol": 985370000
        },
        {
          "time": 1782135000,
          "open": 51555.1914,
          "high": 51887.8516,
          "low": 51555.1914,
          "close": 51712.7109,
          "vol": 529120000
        },
        {
          "time": 1782221400,
          "open": 51735.6406,
          "high": 51872.5586,
          "low": 51301.7695,
          "close": 51666.8398,
          "vol": 548870000
        },
        {
          "time": 1782307800,
          "open": 51660.75,
          "high": 52248.6914,
          "low": 51617.7305,
          "close": 51848.8984,
          "vol": 560271694
        }
      ]
    },
    "ndx": {
      "price": 29220.057,
      "change": -127.2125,
      "pct": -0.43,
      "high": 29592.896,
      "low": 28963.102,
      "vol": 1461500000,
      "candles": [
        {
          "time": 1781703000,
          "open": 30160.7402,
          "high": 30208.9395,
          "low": 29604.9297,
          "close": 29670.9492,
          "vol": 11443600000
        },
        {
          "time": 1781789400,
          "open": 30261.5996,
          "high": 30463.7695,
          "low": 30089.3496,
          "close": 30406.1895,
          "vol": 18286150000
        },
        {
          "time": 1782135000,
          "open": 30529.9902,
          "high": 30642.5703,
          "low": 30194.25,
          "close": 30347.0801,
          "vol": 12844290000
        },
        {
          "time": 1782221400,
          "open": 29369.25,
          "high": 29748.7207,
          "low": 29276.9805,
          "close": 29347.2695,
          "vol": 14631520000
        },
        {
          "time": 1782307800,
          "open": 29328.3984,
          "high": 29592.8965,
          "low": 28963.1016,
          "close": 29220.0566,
          "vol": 1461500000
        }
      ]
    },
    "vix": {
      "price": 18.63,
      "change": -0.86,
      "pct": -4.41,
      "high": 20.34,
      "low": 18.04,
      "vol": 0,
      "candles": [
        {
          "time": 1781766000,
          "open": 17.23,
          "high": 17.6,
          "low": 16.35,
          "close": 16.4,
          "vol": 0
        },
        {
          "time": 1782111600,
          "open": 17.48,
          "high": 17.92,
          "low": 16.49,
          "close": 17.28,
          "vol": 0
        },
        {
          "time": 1782198000,
          "open": 19.67,
          "high": 20.54,
          "low": 18.61,
          "close": 19.49,
          "vol": 0
        },
        {
          "time": 1782284400,
          "open": 19.13,
          "high": 20.34,
          "low": 18.04,
          "close": 18.63,
          "vol": 0
        }
      ]
    },
    "dxy": {
      "price": 101.584,
      "change": 0.174,
      "pct": 0.17,
      "high": 101.8,
      "low": 101.356,
      "vol": 0,
      "candles": [
        {
          "time": 1781755200,
          "open": 100.34,
          "high": 100.92,
          "low": 100.21,
          "close": 100.85,
          "vol": 0
        },
        {
          "time": 1782100800,
          "open": 100.84,
          "high": 101.08,
          "low": 100.76,
          "close": 101.02,
          "vol": 0
        },
        {
          "time": 1782187200,
          "open": 101.01,
          "high": 101.43,
          "low": 100.95,
          "close": 101.41,
          "vol": 0
        },
        {
          "time": 1782273600,
          "open": 101.37,
          "high": 101.8,
          "low": 101.356,
          "close": 101.584,
          "vol": 0
        }
      ]
    },
    "usdkrw": {
      "price": 1539.63,
      "change": 4.38,
      "pct": 0.29,
      "high": 1539.63,
      "low": 1535.91,
      "vol": 0,
      "candles": [
        {
          "time": 1781823600,
          "open": 1535.23,
          "high": 1540.13,
          "low": 1525.09,
          "close": 1537.5601,
          "vol": 0
        },
        {
          "time": 1782082800,
          "open": 1530.04,
          "high": 1541.17,
          "low": 1529.55,
          "close": 1531.33,
          "vol": 0
        },
        {
          "time": 1782169200,
          "open": 1539.54,
          "high": 1541.66,
          "low": 1531.2,
          "close": 1539.05,
          "vol": 0
        },
        {
          "time": 1782255600,
          "open": 1533.3101,
          "high": 1548.27,
          "low": 1533.3101,
          "close": 1535.25,
          "vol": 0
        },
        {
          "time": 1782342000,
          "open": 1536.1801,
          "high": 1539.63,
          "low": 1535.91,
          "close": 1539.63,
          "vol": 0
        }
      ]
    },
    "jpykrw": {
      "price": 9.495,
      "change": -0.0055,
      "pct": -0.06,
      "high": 9.497,
      "low": 9.474,
      "vol": 0,
      "candles": [
        {
          "time": 1781823600,
          "open": 9.5259,
          "high": 9.5623,
          "low": 9.4562,
          "close": 9.5314,
          "vol": 0
        },
        {
          "time": 1782082800,
          "open": 9.4784,
          "high": 9.5329,
          "low": 9.471,
          "close": 9.4854,
          "vol": 0
        },
        {
          "time": 1782169200,
          "open": 9.5324,
          "high": 9.5407,
          "low": 9.4819,
          "close": 9.5248,
          "vol": 0
        },
        {
          "time": 1782255600,
          "open": 9.4918,
          "high": 9.5732,
          "low": 9.4879,
          "close": 9.5005,
          "vol": 0
        },
        {
          "time": 1782342000,
          "open": 9.474,
          "high": 9.497,
          "low": 9.474,
          "close": 9.495,
          "vol": 0
        }
      ]
    },
    "eurkrw": {
      "price": 1747.5,
      "change": 6.9301,
      "pct": 0.4,
      "high": 1747.9,
      "low": 1744.1,
      "vol": 0,
      "candles": [
        {
          "time": 1781823600,
          "open": 1758.34,
          "high": 1762.91,
          "low": 1743.38,
          "close": 1759.48,
          "vol": 0
        },
        {
          "time": 1782082800,
          "open": 1703.52,
          "high": 1763.86,
          "low": 1703.52,
          "close": 1703.52,
          "vol": 0
        },
        {
          "time": 1782169200,
          "open": 1757.9,
          "high": 1759.97,
          "low": 1742.35,
          "close": 1752.54,
          "vol": 0
        },
        {
          "time": 1782255600,
          "open": 1744.75,
          "high": 1755.78,
          "low": 1743.4,
          "close": 1740.5699,
          "vol": 0
        },
        {
          "time": 1782342000,
          "open": 1744.1,
          "high": 1747.9,
          "low": 1744.1,
          "close": 1747.5,
          "vol": 0
        }
      ]
    },
    "gbpkrw": {
      "price": 2024.92,
      "change": -1.5717,
      "pct": -0.08,
      "high": 2025.42,
      "low": 2020.83,
      "vol": 0,
      "candles": [
        {
          "time": 1781823600,
          "open": 2028.2943,
          "high": 2034.0134,
          "low": 2011.5795,
          "close": 2029.4766,
          "vol": 0
        },
        {
          "time": 1782082800,
          "open": 2021.3328,
          "high": 2039.9982,
          "low": 2020.9406,
          "close": 2022.3978,
          "vol": 0
        },
        {
          "time": 1782169200,
          "open": 2039.9357,
          "high": 2041.3066,
          "low": 2019.9407,
          "close": 2038.6406,
          "vol": 0
        },
        {
          "time": 1782255600,
          "open": 2024.5005,
          "high": 2041.124,
          "low": 2023.6554,
          "close": 2026.4917,
          "vol": 0
        },
        {
          "time": 1782342000,
          "open": 2020.83,
          "high": 2025.42,
          "low": 2020.83,
          "close": 2024.92,
          "vol": 0
        }
      ]
    },
    "cnykrw": {
      "price": 226.132,
      "change": -0.234,
      "pct": -0.1,
      "high": 226.132,
      "low": 225.963,
      "vol": 0,
      "candles": [
        {
          "time": 1782343832,
          "open": 226.132,
          "high": 226.132,
          "low": 225.963,
          "close": 226.132,
          "vol": 0
        }
      ]
    },
    "oil": {
      "price": 69.87,
      "change": -3.34,
      "pct": -4.56,
      "high": 70.03,
      "low": 69.66,
      "vol": 980,
      "candles": [
        {
          "time": 1781755200,
          "open": 75.53,
          "high": 76.99,
          "low": 73.58,
          "close": 76.6,
          "vol": 97813
        },
        {
          "time": 1782100800,
          "open": 78.93,
          "high": 78.96,
          "low": 74.45,
          "close": 74.82,
          "vol": 315903
        },
        {
          "time": 1782187200,
          "open": 74.14,
          "high": 74.45,
          "low": 72.48,
          "close": 73.21,
          "vol": 315903
        },
        {
          "time": 1782273600,
          "open": 69.95,
          "high": 70.03,
          "low": 69.66,
          "close": 69.87,
          "vol": 980
        }
      ]
    },
    "brent": {
      "price": 73.12,
      "change": -3.96,
      "pct": -5.14,
      "high": 73.16,
      "low": 73.1,
      "vol": 9,
      "candles": [
        {
          "time": 1781755200,
          "open": 78.35,
          "high": 80.04,
          "low": 76.58,
          "close": 79.85,
          "vol": 31186
        },
        {
          "time": 1782100800,
          "open": 82.21,
          "high": 82.38,
          "low": 77.27,
          "close": 77.9,
          "vol": 46574
        },
        {
          "time": 1782187200,
          "open": 78.06,
          "high": 78.34,
          "low": 76.44,
          "close": 77.08,
          "vol": 46574
        },
        {
          "time": 1782273600,
          "open": 73.1,
          "high": 73.16,
          "low": 73.1,
          "close": 73.12,
          "vol": 9
        }
      ]
    },
    "gold": {
      "price": 4014.0,
      "change": -115.8999,
      "pct": -2.81,
      "high": 4024.9,
      "low": 4006.0,
      "vol": 3725,
      "candles": [
        {
          "time": 1781755200,
          "open": 4279.7998,
          "high": 4323.2002,
          "low": 4223.7002,
          "close": 4224.1001,
          "vol": 738
        },
        {
          "time": 1782100800,
          "open": 4138.7998,
          "high": 4216.3999,
          "low": 4134.7998,
          "close": 4181.8999,
          "vol": 1197
        },
        {
          "time": 1782187200,
          "open": 4127.1001,
          "high": 4135.2002,
          "low": 4118.5,
          "close": 4129.8999,
          "vol": 1197
        },
        {
          "time": 1782273600,
          "open": 4019.0,
          "high": 4024.8999,
          "low": 4006.0,
          "close": 4014.0,
          "vol": 3725
        }
      ]
    },
    "silver": {
      "price": 57.625,
      "change": -4.395,
      "pct": -7.09,
      "high": 57.865,
      "low": 57.4,
      "vol": 1675,
      "candles": [
        {
          "time": 1781755200,
          "open": 66.255,
          "high": 66.255,
          "low": 66.255,
          "close": 66.255,
          "vol": 0
        },
        {
          "time": 1782100800,
          "open": 65.527,
          "high": 65.527,
          "low": 65.527,
          "close": 65.527,
          "vol": 16
        },
        {
          "time": 1782187200,
          "open": 61.95,
          "high": 62.02,
          "low": 61.95,
          "close": 62.02,
          "vol": 16
        },
        {
          "time": 1782273600,
          "open": 57.595,
          "high": 57.865,
          "low": 57.4,
          "close": 57.625,
          "vol": 1675
        }
      ]
    },
    "natgas": {
      "price": 3.271,
      "change": 0.124,
      "pct": 3.94,
      "high": 3.273,
      "low": 3.256,
      "vol": 671,
      "candles": [
        {
          "time": 1781755200,
          "open": 3.154,
          "high": 3.246,
          "low": 3.125,
          "close": 3.233,
          "vol": 147984
        },
        {
          "time": 1782100800,
          "open": 3.28,
          "high": 3.335,
          "low": 3.234,
          "close": 3.253,
          "vol": 151751
        },
        {
          "time": 1782187200,
          "open": 3.237,
          "high": 3.277,
          "low": 3.142,
          "close": 3.147,
          "vol": 151751
        },
        {
          "time": 1782273600,
          "open": 3.263,
          "high": 3.273,
          "low": 3.256,
          "close": 3.271,
          "vol": 671
        }
      ]
    },
    "copper": {
      "price": 5.9785,
      "change": -0.1625,
      "pct": -2.65,
      "high": 5.988,
      "low": 5.971,
      "vol": 264,
      "candles": [
        {
          "time": 1781755200,
          "open": 6.3745,
          "high": 6.3745,
          "low": 6.3745,
          "close": 6.3745,
          "vol": 1031
        },
        {
          "time": 1782100800,
          "open": 6.3565,
          "high": 6.3565,
          "low": 6.3565,
          "close": 6.3565,
          "vol": 1163
        },
        {
          "time": 1782187200,
          "open": 6.178,
          "high": 6.1785,
          "low": 6.123,
          "close": 6.141,
          "vol": 1163
        },
        {
          "time": 1782273600,
          "open": 5.9855,
          "high": 5.988,
          "low": 5.971,
          "close": 5.9785,
          "vol": 264
        }
      ]
    },
    "us10y": {
      "price": 4.402,
      "change": -0.049,
      "pct": -1.1,
      "high": 4.455,
      "low": 4.398,
      "vol": 0,
      "candles": [
        {
          "time": 1781698800,
          "open": 4.443,
          "high": 4.479,
          "low": 4.426,
          "close": 4.463,
          "vol": 0
        },
        {
          "time": 1781785200,
          "open": 4.453,
          "high": 4.453,
          "low": 4.42,
          "close": 4.451,
          "vol": 0
        },
        {
          "time": 1782303600,
          "open": 4.453,
          "high": 4.455,
          "low": 4.398,
          "close": 4.402,
          "vol": 0
        }
      ]
    },
    "us30y": {
      "price": 4.856,
      "change": -0.045,
      "pct": -0.92,
      "high": 4.902,
      "low": 4.849,
      "vol": 0,
      "candles": [
        {
          "time": 1781698800,
          "open": 4.936,
          "high": 4.967,
          "low": 4.91,
          "close": 4.926,
          "vol": 0
        },
        {
          "time": 1781785200,
          "open": 4.871,
          "high": 4.902,
          "low": 4.86,
          "close": 4.901,
          "vol": 0
        },
        {
          "time": 1782303600,
          "open": 4.899,
          "high": 4.902,
          "low": 4.849,
          "close": 4.856,
          "vol": 0
        }
      ]
    },
    "nvda": {
      "price": 199.0,
      "change": -1.04,
      "pct": -0.52,
      "high": 201.65,
      "low": 196.58,
      "vol": 149005898,
      "candles": [
        {
          "time": 1781703000,
          "open": 208.53,
          "high": 209.21,
          "low": 203.08,
          "close": 204.65,
          "vol": 128363500
        },
        {
          "time": 1781789400,
          "open": 207.33,
          "high": 211.39,
          "low": 206.5,
          "close": 210.69,
          "vol": 241272000
        },
        {
          "time": 1782135000,
          "open": 211.44,
          "high": 213.99,
          "low": 207.72,
          "close": 208.65,
          "vol": 122041400
        },
        {
          "time": 1782221400,
          "open": 202.17,
          "high": 203.77,
          "low": 200.0,
          "close": 200.04,
          "vol": 153496200
        },
        {
          "time": 1782307800,
          "open": 200.07,
          "high": 201.65,
          "low": 196.58,
          "close": 199.0,
          "vol": 149005898
        }
      ]
    },
    "aapl": {
      "price": 293.08,
      "change": -1.22,
      "pct": -0.41,
      "high": 299.7,
      "low": 292.94,
      "vol": 46572137,
      "candles": [
        {
          "time": 1781703000,
          "open": 300.85,
          "high": 302.07,
          "low": 294.36,
          "close": 295.95,
          "vol": 42745100
        },
        {
          "time": 1781789400,
          "open": 298.11,
          "high": 300.57,
          "low": 295.62,
          "close": 298.01,
          "vol": 85962200
        },
        {
          "time": 1782135000,
          "open": 297.31,
          "high": 302.42,
          "low": 296.76,
          "close": 297.01,
          "vol": 44879900
        },
        {
          "time": 1782221400,
          "open": 297.54,
          "high": 301.64,
          "low": 294.18,
          "close": 294.3,
          "vol": 52010900
        },
        {
          "time": 1782307800,
          "open": 295.375,
          "high": 299.7,
          "low": 292.94,
          "close": 293.08,
          "vol": 46572137
        }
      ]
    },
    "msft": {
      "price": 365.46,
      "change": -8.48,
      "pct": -2.27,
      "high": 378.88,
      "low": 364.78,
      "vol": 38527409,
      "candles": [
        {
          "time": 1781703000,
          "open": 390.25,
          "high": 390.37,
          "low": 377.32,
          "close": 378.91,
          "vol": 41987800
        },
        {
          "time": 1781789400,
          "open": 377.82,
          "high": 381.37,
          "low": 373.28,
          "close": 379.4,
          "vol": 59714200
        },
        {
          "time": 1782135000,
          "open": 375.74,
          "high": 381.63,
          "low": 367.07,
          "close": 367.34,
          "vol": 45171100
        },
        {
          "time": 1782221400,
          "open": 372.38,
          "high": 377.22,
          "low": 370.67,
          "close": 373.94,
          "vol": 40647600
        },
        {
          "time": 1782307800,
          "open": 371.58,
          "high": 378.88,
          "low": 364.78,
          "close": 365.46,
          "vol": 38527409
        }
      ]
    },
    "tsla": {
      "price": 375.53,
      "change": -6.08,
      "pct": -1.59,
      "high": 384.58,
      "low": 373.05,
      "vol": 35272666,
      "candles": [
        {
          "time": 1781703000,
          "open": 401.53,
          "high": 405.94,
          "low": 393.76,
          "close": 396.38,
          "vol": 43534300
        },
        {
          "time": 1781789400,
          "open": 398.1,
          "high": 402.52,
          "low": 384.7,
          "close": 400.49,
          "vol": 58384700
        },
        {
          "time": 1782135000,
          "open": 394.85,
          "high": 414.75,
          "low": 394.4,
          "close": 405.05,
          "vol": 47819500
        },
        {
          "time": 1782221400,
          "open": 392.61,
          "high": 392.87,
          "low": 379.06,
          "close": 381.61,
          "vol": 50420200
        },
        {
          "time": 1782307800,
          "open": 380.008,
          "high": 384.58,
          "low": 373.05,
          "close": 375.53,
          "vol": 35272666
        }
      ]
    },
    "googl": {
      "price": 345.29,
      "change": -0.84,
      "pct": -0.24,
      "high": 353.476,
      "low": 341.93,
      "vol": 41938315,
      "candles": [
        {
          "time": 1781703000,
          "open": 369.13,
          "high": 372.33,
          "low": 362.02,
          "close": 363.79,
          "vol": 24543600
        },
        {
          "time": 1781789400,
          "open": 365.75,
          "high": 369.48,
          "low": 358.67,
          "close": 368.03,
          "vol": 44470100
        },
        {
          "time": 1782135000,
          "open": 357.95,
          "high": 358.92,
          "low": 341.72,
          "close": 349.68,
          "vol": 52814800
        },
        {
          "time": 1782221400,
          "open": 340.69,
          "high": 349.29,
          "low": 340.2,
          "close": 346.13,
          "vol": 34007700
        },
        {
          "time": 1782307800,
          "open": 348.965,
          "high": 353.476,
          "low": 341.93,
          "close": 345.29,
          "vol": 41938315
        }
      ]
    },
    "meta": {
      "price": 557.67,
      "change": -4.53,
      "pct": -0.81,
      "high": 569.04,
      "low": 555.55,
      "vol": 13155272,
      "candles": [
        {
          "time": 1781703000,
          "open": 592.0,
          "high": 593.81,
          "low": 566.19,
          "close": 567.58,
          "vol": 20478300
        },
        {
          "time": 1781789400,
          "open": 572.82,
          "high": 580.22,
          "low": 563.1,
          "close": 577.22,
          "vol": 28824600
        },
        {
          "time": 1782135000,
          "open": 572.02,
          "high": 575.81,
          "low": 559.81,
          "close": 563.85,
          "vol": 15405500
        },
        {
          "time": 1782221400,
          "open": 562.25,
          "high": 572.2,
          "low": 561.02,
          "close": 562.2,
          "vol": 13103300
        },
        {
          "time": 1782307800,
          "open": 562.15,
          "high": 569.04,
          "low": 555.5503,
          "close": 557.67,
          "vol": 13155272
        }
      ]
    },
    "spy": {
      "price": 733.24,
      "change": -0.34,
      "pct": -0.05,
      "high": 739.945,
      "low": 730.855,
      "vol": 45349023,
      "candles": [
        {
          "time": 1781703000,
          "open": 751.29,
          "high": 752.15,
          "low": 739.22,
          "close": 740.96,
          "vol": 85945200
        },
        {
          "time": 1781789400,
          "open": 747.76,
          "high": 748.23,
          "low": 743.86,
          "close": 746.74,
          "vol": 80875700
        },
        {
          "time": 1782135000,
          "open": 747.7,
          "high": 750.18,
          "low": 743.13,
          "close": 744.39,
          "vol": 46628100
        },
        {
          "time": 1782221400,
          "open": 733.81,
          "high": 739.63,
          "low": 732.3,
          "close": 733.58,
          "vol": 66846800
        },
        {
          "time": 1782307800,
          "open": 735.17,
          "high": 739.945,
          "low": 730.855,
          "close": 733.24,
          "vol": 45349023
        }
      ]
    },
    "qqq": {
      "price": 710.62,
      "change": -3.03,
      "pct": -0.42,
      "high": 719.93,
      "low": 704.45,
      "vol": 39714509,
      "candles": [
        {
          "time": 1781703000,
          "open": 735.19,
          "high": 735.68,
          "low": 720.85,
          "close": 722.51,
          "vol": 51669300
        },
        {
          "time": 1781789400,
          "open": 737.2,
          "high": 741.82,
          "low": 732.51,
          "close": 740.62,
          "vol": 50154600
        },
        {
          "time": 1782135000,
          "open": 742.02,
          "high": 745.45,
          "low": 734.39,
          "close": 737.95,
          "vol": 43518600
        },
        {
          "time": 1782221400,
          "open": 715.74,
          "high": 723.61,
          "low": 712.11,
          "close": 713.65,
          "vol": 53354200
        },
        {
          "time": 1782307800,
          "open": 714.8,
          "high": 719.93,
          "low": 704.45,
          "close": 710.62,
          "vol": 39714509
        }
      ]
    },
    "tlt": {
      "price": 87.38,
      "change": 1.18,
      "pct": 1.37,
      "high": 87.468,
      "low": 87.12,
      "vol": 41707159,
      "candles": [
        {
          "time": 1781703000,
          "open": 86.33,
          "high": 86.59,
          "low": 85.93,
          "close": 86.33,
          "vol": 34507500
        },
        {
          "time": 1781789400,
          "open": 87.07,
          "high": 87.18,
          "low": 86.65,
          "close": 86.75,
          "vol": 32350900
        },
        {
          "time": 1782135000,
          "open": 86.3,
          "high": 86.33,
          "low": 85.97,
          "close": 86.09,
          "vol": 28595100
        },
        {
          "time": 1782221400,
          "open": 86.12,
          "high": 86.43,
          "low": 86.1,
          "close": 86.2,
          "vol": 19145500
        },
        {
          "time": 1782307800,
          "open": 87.14,
          "high": 87.4679,
          "low": 87.12,
          "close": 87.38,
          "vol": 41707159
        }
      ]
    },
    "gld": {
      "price": 365.92,
      "change": -11.4,
      "pct": -3.02,
      "high": 370.88,
      "low": 363.34,
      "vol": 12566894,
      "candles": [
        {
          "time": 1781703000,
          "open": 397.82,
          "high": 402.04,
          "low": 387.08,
          "close": 388.6,
          "vol": 13343000
        },
        {
          "time": 1781789400,
          "open": 391.24,
          "high": 392.5,
          "low": 385.6,
          "close": 387.12,
          "vol": 7627300
        },
        {
          "time": 1782135000,
          "open": 384.25,
          "high": 386.41,
          "low": 382.64,
          "close": 384.59,
          "vol": 7835100
        },
        {
          "time": 1782221400,
          "open": 377.72,
          "high": 380.35,
          "low": 377.17,
          "close": 377.32,
          "vol": 7389600
        },
        {
          "time": 1782307800,
          "open": 364.81,
          "high": 370.88,
          "low": 363.34,
          "close": 365.92,
          "vol": 12566894
        }
      ]
    },
    "eem": {
      "price": 67.25,
      "change": 0.08,
      "pct": 0.12,
      "high": 67.61,
      "low": 66.595,
      "vol": 22931163,
      "candles": [
        {
          "time": 1781703000,
          "open": 69.57,
          "high": 70.08,
          "low": 68.41,
          "close": 68.56,
          "vol": 36131300
        },
        {
          "time": 1781789400,
          "open": 70.18,
          "high": 70.92,
          "low": 70.15,
          "close": 70.79,
          "vol": 49998100
        },
        {
          "time": 1782135000,
          "open": 71.29,
          "high": 71.57,
          "low": 70.99,
          "close": 71.21,
          "vol": 25302200
        },
        {
          "time": 1782221400,
          "open": 67.25,
          "high": 68.23,
          "low": 67.07,
          "close": 67.17,
          "vol": 39069000
        },
        {
          "time": 1782307800,
          "open": 67.38,
          "high": 67.61,
          "low": 66.595,
          "close": 67.25,
          "vol": 22931163
        }
      ]
    },
    "xle": {
      "price": 53.57,
      "change": -0.89,
      "pct": -1.63,
      "high": 53.765,
      "low": 52.94,
      "vol": 42799653,
      "candles": [
        {
          "time": 1781703000,
          "open": 55.26,
          "high": 55.36,
          "low": 54.54,
          "close": 54.67,
          "vol": 38553000
        },
        {
          "time": 1781789400,
          "open": 54.14,
          "high": 54.25,
          "low": 53.25,
          "close": 53.77,
          "vol": 39645700
        },
        {
          "time": 1782135000,
          "open": 53.53,
          "high": 54.13,
          "low": 53.17,
          "close": 54.06,
          "vol": 30765600
        },
        {
          "time": 1782221400,
          "open": 54.14,
          "high": 54.56,
          "low": 53.87,
          "close": 54.46,
          "vol": 38690400
        },
        {
          "time": 1782307800,
          "open": 53.5,
          "high": 53.765,
          "low": 52.94,
          "close": 53.57,
          "vol": 42799653
        }
      ]
    },
    "samsung": {
      "price": 340500.0,
      "change": 30500.0,
      "pct": 9.84,
      "high": 0.0,
      "low": 0.0,
      "vol": 0,
      "candles": [
        {
          "time": 1781740800,
          "open": 345000.0,
          "high": 363000.0,
          "low": 344500.0,
          "close": 362500.0,
          "vol": 32764450
        },
        {
          "time": 1781827200,
          "open": 372500.0,
          "high": 374500.0,
          "low": 346250.0,
          "close": 354000.0,
          "vol": 43284898
        },
        {
          "time": 1782086400,
          "open": 343000.0,
          "high": 363000.0,
          "low": 342000.0,
          "close": 353500.0,
          "vol": 24330451
        },
        {
          "time": 1782172800,
          "open": 347500.0,
          "high": 353000.0,
          "low": 310000.0,
          "close": 310000.0,
          "vol": 41266630
        },
        {
          "time": 1782259200,
          "open": 314000.0,
          "high": 341000.0,
          "low": 314000.0,
          "close": 340500.0,
          "vol": 47809959
        }
      ]
    },
    "hynix": {
      "price": 2580000.0,
      "change": 25000.0,
      "pct": 0.98,
      "high": 0.0,
      "low": 0.0,
      "vol": 0,
      "candles": [
        {
          "time": 1781740800,
          "open": 2556000.0,
          "high": 2738000.0,
          "low": 2556000.0,
          "close": 2685000.0,
          "vol": 5808765
        },
        {
          "time": 1781827200,
          "open": 2824000.0,
          "high": 2891000.0,
          "low": 2688000.0,
          "close": 2764000.0,
          "vol": 7478195
        },
        {
          "time": 1782086400,
          "open": 2728000.0,
          "high": 2945000.0,
          "low": 2728000.0,
          "close": 2919000.0,
          "vol": 5179795
        },
        {
          "time": 1782172800,
          "open": 2898000.0,
          "high": 2943000.0,
          "low": 2536000.0,
          "close": 2555000.0,
          "vol": 8050335
        },
        {
          "time": 1782259200,
          "open": 2598000.0,
          "high": 2703000.0,
          "low": 2453000.0,
          "close": 2621000.0,
          "vol": 7487916
        }
      ]
    },
    "hanwha": {
      "price": 1094000.0,
      "change": 21000.0,
      "pct": 1.96,
      "high": 0.0,
      "low": 0.0,
      "vol": 0,
      "candles": [
        {
          "time": 1781740800,
          "open": 1235000.0,
          "high": 1242000.0,
          "low": 1183000.0,
          "close": 1189000.0,
          "vol": 255178
        },
        {
          "time": 1781827200,
          "open": 1189000.0,
          "high": 1198500.0,
          "low": 1095000.0,
          "close": 1122000.0,
          "vol": 456658
        },
        {
          "time": 1782086400,
          "open": 1186000.0,
          "high": 1192000.0,
          "low": 1122000.0,
          "close": 1125000.0,
          "vol": 145874
        },
        {
          "time": 1782172800,
          "open": 1124000.0,
          "high": 1145000.0,
          "low": 1064000.0,
          "close": 1073000.0,
          "vol": 198818
        },
        {
          "time": 1782259200,
          "open": 1063000.0,
          "high": 1101000.0,
          "low": 1032000.0,
          "close": 1094000.0,
          "vol": 177303
        }
      ]
    },
    "lignex": {
      "price": 824000.0,
      "change": 15000.0,
      "pct": 1.85,
      "high": 0.0,
      "low": 0.0,
      "vol": 0,
      "candles": [
        {
          "time": 1781740800,
          "open": 936000.0,
          "high": 937000.0,
          "low": 873000.0,
          "close": 884000.0,
          "vol": 246830
        },
        {
          "time": 1781827200,
          "open": 870000.0,
          "high": 878000.0,
          "low": 831000.0,
          "close": 852000.0,
          "vol": 177739
        },
        {
          "time": 1782086400,
          "open": 874000.0,
          "high": 884000.0,
          "low": 840000.0,
          "close": 848000.0,
          "vol": 121432
        },
        {
          "time": 1782172800,
          "open": 840000.0,
          "high": 879000.0,
          "low": 806000.0,
          "close": 809000.0,
          "vol": 178084
        },
        {
          "time": 1782259200,
          "open": 802000.0,
          "high": 838000.0,
          "low": 782000.0,
          "close": 824000.0,
          "vol": 133804
        }
      ]
    },
    "rainbow": {
      "price": 515000.0,
      "change": 12000.0,
      "pct": 2.39,
      "high": 0.0,
      "low": 0.0,
      "vol": 0,
      "candles": [
        {
          "time": 1781740800,
          "open": 635000.0,
          "high": 637000.0,
          "low": 603000.0,
          "close": 615000.0,
          "vol": 77337
        },
        {
          "time": 1781827200,
          "open": 608000.0,
          "high": 611000.0,
          "low": 573000.0,
          "close": 590000.0,
          "vol": 124349
        },
        {
          "time": 1782086400,
          "open": 587000.0,
          "high": 590000.0,
          "low": 563000.0,
          "close": 573000.0,
          "vol": 86658
        },
        {
          "time": 1782172800,
          "open": 565000.0,
          "high": 579000.0,
          "low": 501000.0,
          "close": 503000.0,
          "vol": 156483
        },
        {
          "time": 1782259200,
          "open": 522000.0,
          "high": 532000.0,
          "low": 501000.0,
          "close": 515000.0,
          "vol": 102908
        }
      ]
    },
    "doosanrobo": {
      "price": 95000.0,
      "change": 6200.0,
      "pct": 6.98,
      "high": 0.0,
      "low": 0.0,
      "vol": 0,
      "candles": [
        {
          "time": 1781740800,
          "open": 108600.0,
          "high": 108900.0,
          "low": 102100.0,
          "close": 102700.0,
          "vol": 544190
        },
        {
          "time": 1781827200,
          "open": 102400.0,
          "high": 103900.0,
          "low": 98000.0,
          "close": 101800.0,
          "vol": 1103887
        },
        {
          "time": 1782086400,
          "open": 100500.0,
          "high": 101800.0,
          "low": 99100.0,
          "close": 100400.0,
          "vol": 416677
        },
        {
          "time": 1782172800,
          "open": 99400.0,
          "high": 100600.0,
          "low": 88200.0,
          "close": 88800.0,
          "vol": 812751
        },
        {
          "time": 1782259200,
          "open": 95000.0,
          "high": 100600.0,
          "low": 90600.0,
          "close": 95000.0,
          "vol": 1100505
        }
      ]
    },
    "samsungbio": {
      "price": 1385000.0,
      "change": 112000.0,
      "pct": 8.8,
      "high": 0.0,
      "low": 0.0,
      "vol": 0,
      "candles": [
        {
          "time": 1781740800,
          "open": 1376000.0,
          "high": 1456000.0,
          "low": 1362000.0,
          "close": 1430000.0,
          "vol": 113690
        },
        {
          "time": 1781827200,
          "open": 1442000.0,
          "high": 1443000.0,
          "low": 1346000.0,
          "close": 1374000.0,
          "vol": 99207
        },
        {
          "time": 1782086400,
          "open": 1374000.0,
          "high": 1374000.0,
          "low": 1290000.0,
          "close": 1295000.0,
          "vol": 51541
        },
        {
          "time": 1782172800,
          "open": 1300000.0,
          "high": 1344000.0,
          "low": 1270000.0,
          "close": 1273000.0,
          "vol": 61840
        },
        {
          "time": 1782259200,
          "open": 1290000.0,
          "high": 1396000.0,
          "low": 1258000.0,
          "close": 1385000.0,
          "vol": 95518
        }
      ]
    },
    "celltrion": {
      "price": 172700.0,
      "change": 12200.0,
      "pct": 7.6,
      "high": 0.0,
      "low": 0.0,
      "vol": 0,
      "candles": [
        {
          "time": 1781740800,
          "open": 173200.0,
          "high": 175500.0,
          "low": 172300.0,
          "close": 173600.0,
          "vol": 443187
        },
        {
          "time": 1781827200,
          "open": 173000.0,
          "high": 174100.0,
          "low": 166500.0,
          "close": 170300.0,
          "vol": 1160752
        },
        {
          "time": 1782086400,
          "open": 168400.0,
          "high": 169200.0,
          "low": 166300.0,
          "close": 168500.0,
          "vol": 503668
        },
        {
          "time": 1782172800,
          "open": 167700.0,
          "high": 169900.0,
          "low": 160300.0,
          "close": 160500.0,
          "vol": 580032
        },
        {
          "time": 1782259200,
          "open": 160500.0,
          "high": 175500.0,
          "low": 159200.0,
          "close": 172700.0,
          "vol": 824946
        }
      ]
    }
  },
  "news": [
    {
      "source": "매일경제",
      "category": "분석",
      "title": "이젠 보험까지 담보잡고 주식한다…빚투 광풍에 보험사들 긴급소집",
      "link": "https://www.mk.co.kr/news/economy/12082585",
      "summary": "[배경/맥락] 개인투자자들이 보험을 담보로 대출받아 주식투자를 하는 빚투 현상이 확산되면서 보험사들이 긴급 대응에 나섰다.\n\n[투자 시사점] 이는 시장 과열과 개인투자자의 레버리지 위험 증가를 의미하므로 투자자들은 차입금을 통한 투자의 손실 위험을 신중히 검토해야"
    },
    {
      "source": "매일경제",
      "category": "분석",
      "title": "국민성장펀드 뒷받침하는 연기금…일주일만에 1100억 투자",
      "link": "https://www.mk.co.kr/news/economy/12082244",
      "summary": "**[배경/맥락]** 정부의 국민성장펀드 조성을 위해 연기금이 일주일 만에 1100억 원을 투자하며 적극적으로 지원하고 있다.\n\n**[투자 시사점]** 연기금의 신속한 자금 투입은 정부 정책 펀드에 대한 기관투자자의 신뢰도를 반영하며, 향후 추가 자금 유입 가능성을 시사한"
    },
    {
      "source": "매일경제",
      "category": "분석",
      "title": "[표] 외국환율고시표",
      "link": "https://www.mk.co.kr/news/economy/12082216",
      "summary": "# 외국환율고시표 분석\n\n[배경/맥락] 한국은행이 공시하는 외국환율고시표는 주요 통화별 환율을 일일 기준으로 제시하는 공식 지표입니다. [투자 시사점] 투자자들은 이 기준환율을 통해 환헤지 전략 수립, 해외자산 평가, 환차익 거래 판단의 기초 자료로 활용할 수 있습니다"
    },
    {
      "source": "매일경제",
      "category": "분석",
      "title": "환율 불안한데 … MSCI 선진국지수 또 불발",
      "link": "https://www.mk.co.kr/news/economy/12082213",
      "summary": "[배경/맥락] 환율 변동성이 높아지는 불안정한 시장 상황에서 MSCI 선진국지수가 예상된 상승을 달성하지 못했다.\n\n[투자 시사점] 환율 리스크와 선진국 주식의 약세가 겹치면서 해외 주식 투자자들의 수익성이 제약될 수 있으므로 환헤지 전략 검토가 필요하다."
    },
    {
      "source": "파이낸셜뉴스",
      "category": "분석",
      "title": "\"널뛰기 증시 불안하네\"…코스피 변동성지수 역대 최고치",
      "link": "https://www.fnnews.com/news/202606241840123887",
      "summary": "**[배경/맥락]** 코스피 변동성지수(VIX)가 역대 최고치를 기록하며 증시가 급락과 급등을 반복하는 불안정한 상황이 발생했습니다. **[투자 시사점]** 투자자들은 포트폴리오 리스크 관리를 강화하고 변동성 확대에 대비한 헤징 전략을 검토할 필요가 있습니다."
    },
    {
      "source": "파이낸셜뉴스",
      "category": "분석",
      "title": "\"정신 나갈 것 같다\"…'레버리지 ETF'에 멘탈 털린 개미들 [월급쟁이 희노애락]",
      "link": "https://www.fnnews.com/news/202606250539440298",
      "summary": "# 레버리지 ETF 투자자 심리 분석\n\n[배경/맥락] 레버리지 ETF에 투자한 개인투자자들이 심각한 손실로 인한 심리적 어려움을 겪고 있다.\n\n[투자 시사점] 높은 수익률을 추구하는 레버리지 상품은 변동성이 크므로 투자자는 자신의 위험 감수 능력을 정확히 파악하고 신중한"
    },
    {
      "source": "파이낸셜뉴스",
      "category": "분석",
      "title": "삼성전자, 美ADR 상장이 촉매…목표가 계속 오른다 [종목 돋보기]",
      "link": "https://www.fnnews.com/news/202606250754214794",
      "summary": "[배경/맥락] 삼성전자가 미국 ADR(American Depositary Receipt) 상장을 추진하면서 증권사들의 목표가 상향 조정이 이어지고 있다.\n\n[투자 시사점] 미국 시장 직접 상장은 글로벌 투자자 접근성 확대와 유동성 증대로 주가 상승 요인이 될 수 있다."
    },
    {
      "source": "파이낸셜뉴스",
      "category": "분석",
      "title": "[속보] 코스피, 152.95p(1.86%) 오른 8356.79 출발",
      "link": "https://www.fnnews.com/news/202606240853565969",
      "summary": "[배경/맥락] 코스피 지수가 152.95포인트 상승하여 8356.79로 장을 시작했으며, 이는 전날 대비 1.86%의 상승률을 기록한 것입니다. [투자 시사점] 긍정적인 장 출발은 시장 심리 개선을 시사하므로 투자자들은 이러한 상승 추세의 지속 여부를 주시하며 포지셔닝을 검토"
    },
    {
      "source": "파이낸셜뉴스",
      "category": "국제",
      "title": "월가, S&P500 목표가 잇달아 상향…JP모건 '플래시 크래시' 경고",
      "link": "https://www.fnnews.com/news/202606250235344233",
      "summary": "**[배경/맥락]** 월가 주요 투자은행들이 S&P500의 목표가를 연이어 상향 조정하고 있으며, 동시에 JP모건은 급락 위험을 경고하고 있다.\n\n**[투자 시사점]** 이는 시장의 강세 전망과 변동성 리스크가 공존하고 있음을 의미하므로, 투자자들은 상승 기회와 함께 하락 시나리오"
    },
    {
      "source": "파이낸셜뉴스",
      "category": "국제",
      "title": "AI 빅테크, 6월 한 달 시총 4169조원 사라져…\"막대한 투자 감당할까\"",
      "link": "https://www.fnnews.com/news/202606250329123367",
      "summary": "[배경/맥락] AI 분야 주도 기업들의 시가총액이 6월 한 달간 4169조원 감소했으며, 이는 이들 기업의 막대한 투자 비용 감당 능력에 대한 시장의 우려를 반영하고 있습니다.\n\n[투자 시사점] 투자자들은 AI 빅테크 기업들의 수익성 개선 시점과 투자 수익률 실현 가능성을 면"
    },
    {
      "source": "파이낸셜뉴스",
      "category": "국제",
      "title": "[국제유가] 4% 안팎 급락…트럼프\"정유사들, 소비자 바가지\"",
      "link": "https://www.fnnews.com/news/202606250448135865",
      "summary": "**[배경/맥락]** 국제유가가 4% 안팎으로 급락했으며, 트럼프 전 대통령이 정유사들이 소비자에게 과도한 마진을 취하고 있다고 지적했습니다.\n\n**[투자 시사점]** 유가 하락에도 불구하고 정유사의 마진 관행이 문제가 되면 향후 규제 강화나 가격 통제 정책이 추진될 수"
    },
    {
      "source": "파이낸셜뉴스",
      "category": "국제",
      "title": "[속보][뉴욕증시] 다우지수만 반등…반도체, 하락 진정",
      "link": "https://www.fnnews.com/news/202606250502232869",
      "summary": "[배경/맥락] 뉴욕증시에서 다우지수는 반등했으나 반도체 섹터는 계속 하락세를 보이고 있습니다. [투자 시사점] 투자자들은 경기 방어주 중심의 다우지수와 성장주 중심의 반도체 섹터 간 성과 차이를 고려하여 포트폴리오 구성을 재검토할 필요가 있습니다."
    },
    {
      "source": "Investing.com",
      "category": "속보",
      "title": "Faeth Therapeutics CFO 브라이언 C. 스티븐슨, 405,920달러 규모 자사주 매입",
      "link": "https://kr.investing.com/news/insider-trading-news/article-93CH-1995124",
      "summary": "[배경/맥락] Faeth Therapeutics의 CFO 브라이언 C. 스티븐슨이 405,920달러 규모의 자사주를 매입했습니다. [투자 시사점] 경영진의 자사주 매입은 회사의 주가가 저평가되었다고 판단하는 신호로 해석될 수 있으며, 경영진의 자신감을 나타내는 긍정적 지표입니다."
    },
    {
      "source": "Investing.com",
      "category": "속보",
      "title": "Ooma 이사 러셀 만, 회사 주식 367,013달러 매각",
      "link": "https://kr.investing.com/news/insider-trading-news/article-93CH-1995123",
      "summary": "[배경/맥락] Ooma의 이사인 러셀 만이 회사 주식 367,013달러 규모를 매각했습니다. [투자 시사점] 경영진의 주식 매각은 회사에 대한 신뢰도 변화를 시장에 신호할 수 있으므로 투자자들은 매각 규모와 시점, 회사의 펀더멘탈 변화를 함께 검토할 필요가 있습니다."
    },
    {
      "source": "Investing.com",
      "category": "속보",
      "title": "Faeth 테라퓨틱스 CEO 아난드 파리크, 보통주 55,446달러 매입",
      "link": "https://kr.investing.com/news/insider-trading-news/article-93CH-1995122",
      "summary": "**[배경/맥락]** Faeth Therapeutics의 CEO 아난드 파리크가 보통주 55,446달러 규모를 매입했다.\n\n**[투자 시사점]** 경영진의 자사주 매입은 회사 전망에 대한 긍정적 신호로 해석될 수 있으며, 주가 상승 가능성을 시사한다."
    },
    {
      "source": "Investing.com",
      "category": "속보",
      "title": "아리스타 네트웍스 사장 겸 CTO 케네스 두다, 740만 달러 주식 매도",
      "link": "https://kr.investing.com/news/insider-trading-news/article-93CH-1995119",
      "summary": "[배경/맥락] 아리스타 네트웍스의 주요 경영진인 케네스 두다 사장 겸 CTO가 740만 달러 규모의 자사주를 매도했다. [투자 시사점] 경영진의 주식 매도는 회사 내부자의 주가 전망을 반영하는 신호로 작용할 수 있으므로 투자자들은 이러한 거래 동향과 함께 회사의 펀더"
    },
    {
      "source": "한국경제",
      "category": "국내",
      "title": "미국 기업이익 사상 최고…증시 강세 뒤 숨은 '경고음'",
      "link": "https://www.hankyung.com/article/202606256656i",
      "summary": "**[배경/맥락]** 미국 기업들의 이익이 사상 최고 수준을 기록하면서 증시가 강세를 보이고 있습니다. **[투자 시사점]** 다만 이러한 실적 호조 뒤에 숨겨진 부정적 신호들이 존재하므로 투자자들은 시장의 겉보기 강세에만 의존하지 말고 기저 리스크를 점검할 필요가"
    },
    {
      "source": "한국경제",
      "category": "국내",
      "title": "[외신 에스프레소 영상] 아시아 대륙 덮친 '슈퍼 엘니뇨' 공포…인도 설탕 수출 중단",
      "link": "https://www.hankyung.com/article/202606256638i",
      "summary": "[배경/맥락] 슈퍼 엘니뇨 현상으로 인한 가뭄이 아시아를 덮치면서 인도가 설탕 수출을 중단했다.\n\n[투자 시사점] 주요 설탕 수출국의 공급 차질로 글로벌 설탕 가격 상승이 예상되며, 설탕 관련 기업과 식품업체의 원가 부담 증가가 투자 판단의 주"
    },
    {
      "source": "한국경제",
      "category": "국내",
      "title": "\"SK하이닉스, ADR 나스닥 입성 따른 주가 재평가 기대\"-삼성",
      "link": "https://www.hankyung.com/article/2026062566466",
      "summary": "[배경/맥락] SK하이닉스가 미국 나스닥에 ADR(미국예탁증권)을 상장함으로써 글로벌 투자자들의 접근성이 높아졌다.\n\n[투자 시사점] 나스닥 상장으로 인한 국제적 인지도 상승과 유동성 증대가 주가 재평가로 이어질 수 있다는 긍정적 전망이 제시되고 있다."
    },
    {
      "source": "한국경제",
      "category": "국내",
      "title": "기술주 부담에 나스닥 하락…항공주는 급등",
      "link": "https://www.hankyung.com/article/202606256564i",
      "summary": "[배경/맥락] 나스닥이 기술주의 약세로 하락했으나, 항공주는 급등하며 시장 내 섹터 간 성과 차이가 발생했다.\n\n[투자 시사점] 투자자들은 기술주 중심의 포트폴리오 재검토와 함께 항공 등 경기민감주의 상대적 강세 추세를 고려한 자산배분 조정이 필요하다."
    },
    {
      "source": "연합뉴스",
      "category": "국내",
      "title": "IBK투자 \"LG디스플레이, 3분기부터 흑자전환해 실적개선 전망\"",
      "link": "https://www.yna.co.kr/view/AKR20260625024800008",
      "summary": "[배경/맥락] IBK투자가 LG디스플레이의 3분기부터 흑자전환을 예상하며 실적 개선 전망을 제시했다.\n\n[투자 시사점] 적자 상황에서 벗어나 수익성 회복이 예상되므로 실적 개선에 따른 주가 상승 가능성을 고려할 수 있다."
    },
    {
      "source": "연합뉴스",
      "category": "국내",
      "title": "[부산소식] 해양신산업 선도 분야 발굴 사업 2차 공모",
      "link": "https://www.yna.co.kr/view/AKR20260625020100051",
      "summary": "[배경/맥락] 부산이 해양신산업의 선도 분야를 발굴하기 위해 2차 공모 사업을 진행하고 있습니다. [투자 시사점] 해양산업 관련 기업과 스타트업들에게 정부 지원 기회가 확대되고 있어 해당 분야 투자 생태계 성장 가능성을 시사합니다."
    },
    {
      "source": "연합뉴스",
      "category": "국내",
      "title": "TKG휴켐스 \"에이프릴바이오 주식 1천500억원에 취득\"",
      "link": "https://www.yna.co.kr/view/AKR20260625018700008",
      "summary": "[배경/맥락] TKG휴켐스가 에이프릴바이오의 주식을 1천500억원 규모로 취득하는 전략적 투자를 단행했다. [투자 시사점] 이는 TKG휴켐스가 바이오 부문 포트폴리오를 확대하려는 의도로 해석되며, 해당 기업들의 주가와 사업 시너지에 영향을 미칠 수 있다."
    },
    {
      "source": "연합뉴스",
      "category": "국내",
      "title": "[마켓뷰] 마이크론 어닝 서프라이즈…코스피 9,000 탈환 시도하나",
      "link": "https://www.yna.co.kr/view/AKR20260625016900008",
      "summary": "[배경/맥락] 마이크론이 시장 예상을 상회하는 실적을 발표하면서 반도체 업종에 긍정적 신호를 전달했다. [투자 시사점] 이는 국내 반도체 기업들의 실적 개선 기대감으로 이어져 코스피 지수가 9,000선 회복을 시도할 수 있는 모멘텀이 될 수 있다."
    }
  ],
  "portfolio": {
    "holdings": [
      {
        "시장": "국내",
        "종목명": "SK하이닉스",
        "섹터": "반도체",
        "코드": "000660",
        "보유량": "14",
        "매수평단가": "1,355,857.14",
        "매수총액($)": "18,982,000.00",
        "매수평단가(원)": "1,355,857",
        "매수총액(원)": "18,982,000",
        "평균환율": "1.00",
        "현재가": "₩",
        "": "-",
        "평가총액": "₩",
        "평가총액(원)": "₩ 36,120,000",
        "총수익": "₩",
        "원화수익": "₩ 17,138,000",
        "일간수익": ""
      },
      {
        "시장": "국내",
        "종목명": "삼성전자",
        "섹터": "반도체",
        "코드": "005930",
        "보유량": "40",
        "매수평단가": "212,111.88",
        "매수총액($)": "8,484,475.00",
        "매수평단가(원)": "212,112",
        "매수총액(원)": "8,484,475",
        "평균환율": "1.00",
        "현재가": "₩",
        "": "-",
        "평가총액": "₩",
        "평가총액(원)": "₩ 13,620,000",
        "총수익": "₩",
        "원화수익": "₩ 5,135,525",
        "일간수익": ""
      },
      {
        "시장": "미국",
        "종목명": "브로드컴",
        "섹터": "반도체",
        "코드": "AVGO",
        "보유량": "18",
        "매수평단가": "195.34",
        "매수총액($)": "3,516.10",
        "매수평단가(원)": "300,687",
        "매수총액(원)": "5,412,369",
        "평균환율": "",
        "현재가": "$",
        "": "(+0.51%)",
        "평가총액": "$",
        "평가총액(원)": "₩ 10,586,512",
        "총수익": "$",
        "원화수익": "₩ 5,174,144",
        "일간수익": "▲1.93"
      },
      {
        "시장": "국내",
        "종목명": "삼성전기",
        "섹터": "전기/전자",
        "코드": "009150",
        "보유량": "5",
        "매수평단가": "896,000.00",
        "매수총액($)": "4,480,000.00",
        "매수평단가(원)": "896,000",
        "매수총액(원)": "4,480,000",
        "평균환율": "1.00",
        "현재가": "₩",
        "": "-",
        "평가총액": "₩",
        "평가총액(원)": "₩ 9,820,000",
        "총수익": "₩",
        "원화수익": "₩ 5,340,000",
        "일간수익": ""
      },
      {
        "시장": "미국",
        "종목명": "애플",
        "섹터": "기술주",
        "코드": "AAPL",
        "보유량": "15",
        "매수평단가": "218.31",
        "매수총액($)": "3,274.61",
        "매수평단가(원)": "336,043",
        "매수총액(원)": "5,040,640",
        "평균환율": "",
        "현재가": "$",
        "": "(-0.38%)",
        "평가총액": "$",
        "평가총액(원)": "₩ 6,769,193",
        "총수익": "$",
        "원화수익": "₩ 1,728,553",
        "일간수익": "▼1.13"
      },
      {
        "시장": "미국",
        "종목명": "엔비디아",
        "섹터": "반도체",
        "코드": "NVDA",
        "보유량": "20",
        "매수평단가": "129.31",
        "매수총액($)": "2,586.20",
        "매수평단가(원)": "199,048",
        "매수총액(원)": "3,980,964",
        "평균환율": "",
        "현재가": "$",
        "": "(-0.52%)",
        "평가총액": "$",
        "평가총액(원)": "₩ 6,126,454",
        "총수익": "$",
        "원화수익": "₩ 2,145,490",
        "일간수익": "▼1.04"
      },
      {
        "시장": "미국",
        "종목명": "마이크로소프트",
        "섹터": "클라우드",
        "코드": "MSFT",
        "보유량": "10",
        "매수평단가": "430.11",
        "매수총액($)": "4,301.15",
        "매수평단가(원)": "662,080",
        "매수총액(원)": "6,620,797",
        "평균환율": "",
        "현재가": "$",
        "": "(-2.27%)",
        "평가총액": "$",
        "평가총액(원)": "₩ 5,625,562",
        "총수익": "$",
        "원화수익": "₩ -995,234",
        "일간수익": "▼8.48"
      },
      {
        "시장": "국내",
        "종목명": "한국전력",
        "섹터": "전력",
        "코드": "015760",
        "보유량": "150",
        "매수평단가": "19,276.67",
        "매수총액($)": "2,891,500.00",
        "매수평단가(원)": "19,277",
        "매수총액(원)": "2,891,500",
        "평균환율": "1.00",
        "현재가": "₩",
        "": "(+1.38%)",
        "평가총액": "₩",
        "평가총액(원)": "₩ 5,512,500",
        "총수익": "₩",
        "원화수익": "₩ 2,621,000",
        "일간수익": "▲500.00"
      },
      {
        "시장": "미국",
        "종목명": "테슬라",
        "섹터": "자동차",
        "코드": "TSLA",
        "보유량": "7",
        "매수평단가": "428.74",
        "매수총액($)": "3,001.21",
        "매수평단가(원)": "659,970",
        "매수총액(원)": "4,619,793",
        "평균환율": "",
        "현재가": "$",
        "": "(-1.59%)",
        "평가총액": "$",
        "평가총액(원)": "₩ 4,046,400",
        "총수익": "$",
        "원화수익": "₩ -573,393",
        "일간수익": "▼6.08"
      },
      {
        "시장": "미국",
        "종목명": "TSMC",
        "섹터": "반도체",
        "코드": "TSM",
        "보유량": "4",
        "매수평단가": "185.03",
        "매수총액($)": "740.13",
        "매수평단가(원)": "284,822",
        "매수총액(원)": "1,139,286",
        "평균환율": "",
        "현재가": "$",
        "": "(+1.02%)",
        "평가총액": "$",
        "평가총액(원)": "₩ 2,714,296",
        "총수익": "$",
        "원화수익": "₩ 1,575,010",
        "일간수익": "▲4.44"
      },
      {
        "시장": "미국",
        "종목명": "IVV_S&P500",
        "섹터": "S&P500",
        "코드": "IVV",
        "보유량": "2",
        "매수평단가": "599.00",
        "매수총액($)": "1,198.00",
        "매수평단가(원)": "922,047",
        "매수총액(원)": "1,844,093",
        "평균환율": "",
        "현재가": "$",
        "": "(-0.07%)",
        "평가총액": "$",
        "평가총액(원)": "₩ 2,267,896",
        "총수익": "$",
        "원화수익": "₩ 423,803",
        "일간수익": "▼0.48"
      },
      {
        "시장": "국내",
        "종목명": "네이버",
        "섹터": "기술주",
        "코드": "035420",
        "보유량": "7",
        "매수평단가": "189,500.00",
        "매수총액($)": "1,326,500.00",
        "매수평단가(원)": "189,500",
        "매수총액(원)": "1,326,500",
        "평균환율": "1.00",
        "현재가": "₩",
        "": "(-1.53%)",
        "평가총액": "₩",
        "평가총액(원)": "₩ 1,395,800",
        "총수익": "₩",
        "원화수익": "₩ 69,300",
        "일간수익": "▼3,100.00"
      },
      {
        "시장": "미국",
        "종목명": "코카콜라",
        "섹터": "음료",
        "코드": "KO",
        "보유량": "10",
        "매수평단가": "65.36",
        "매수총액($)": "653.60",
        "매수평단가(원)": "100,609",
        "매수총액(원)": "1,006,093",
        "평균환율": "",
        "현재가": "$",
        "": "(+0.35%)",
        "평가총액": "$",
        "평가총액(원)": "₩ 1,240,684",
        "총수익": "$",
        "원화수익": "₩ 234,591",
        "일간수익": "▲0.28"
      },
      {
        "시장": "국내",
        "종목명": "현대차",
        "섹터": "자동차",
        "코드": "005380",
        "보유량": "2",
        "매수평단가": "274,500.00",
        "매수총액($)": "549,000.00",
        "매수평단가(원)": "274,500",
        "매수총액(원)": "549,000",
        "평균환율": "1.00",
        "현재가": "₩",
        "": "(-0.39%)",
        "평가총액": "₩",
        "평가총액(원)": "₩ 1,018,000",
        "총수익": "₩",
        "원화수익": "₩ 469,000",
        "일간수익": "▼2,000.00"
      },
      {
        "시장": "미국",
        "종목명": "NVDL",
        "섹터": "반도체",
        "코드": "NVDL",
        "보유량": "6",
        "매수평단가": "66.16",
        "매수총액($)": "396.97",
        "매수평단가(원)": "101,843",
        "매수총액(원)": "611,058",
        "평균환율": "",
        "현재가": "$",
        "": "(-1.42%)",
        "평가총액": "$",
        "평가총액(원)": "₩ 820,606",
        "총수익": "$",
        "원화수익": "₩ 209,548",
        "일간수익": "▼1.28"
      },
      {
        "시장": "미국",
        "종목명": "월마트",
        "섹터": "도소매",
        "코드": "WMT",
        "보유량": "2",
        "매수평단가": "93.79",
        "매수총액($)": "187.58",
        "매수평단가(원)": "144,372",
        "매수총액(원)": "288,744",
        "평균환율": "",
        "현재가": "$",
        "": "(-0.35%)",
        "평가총액": "$",
        "평가총액(원)": "₩ 366,356",
        "총수익": "$",
        "원화수익": "₩ 77,612",
        "일간수익": "▼0.42"
      }
    ],
    "count": 16
  },
  "ai": {
    "summary": "코스피가 **-7.06%** 급락하며 **8,471p**까지 밀렸으나, 삼성전자(+9.84%)와 삼성바이오로직스(+8.8%) 등 대형주 일부가 강한 반등을 보이며 시장 내 극심한 차별화가 진행 중이다. 미국 시장은 상대적으로 안정적이나 원자재(은 -7.09%, 유가 -4.56%)와 금(-2.81%) 동반 하락이 글로벌 위험 회피 심리를 반영하고 있다.",
    "kr": "한국 시장 분석:\n1. **코스피 8,471p(-7.06%)**, **코스닥 909p(-6.1%)** 로 두 지수 모두 대규모 낙폭을 기록하며 극도의 패닉 장세가 연출됐다. 단일 세션 7% 이상 하락은 매우 이례적이며 시장 전반의 투매 압력이 강하게 작용했음을 시사한다.\n2. **달러/원 1,539.63원(+0.29%)** 으로 원화 약세가 지속되고 있어 외국인 자금의 추가 이탈 가능성을 높이고 있다. 환율 상승은 수입 물가 부담과 외국인 수익률 훼손으로 연결되어 지수 하방 압력을 가중시킨다.\n3. 지수 급락 속에서도 **삼성전자 340,500원(+9.84%)**, **삼성바이오로직스 1,385,000원(+8.8%)**, **셀트리온 172,700원(+7.6%)** 등 대형 우량주 일부가 강하게 반등하며 저가 매수 유입이 확인됐다. **한화 1,094,000원(+1.96%)**, **SK하이닉스 2,580,000원(+0.98%)** 도 소폭 플러스로 방어했다.\n4. 지수 급락과 일부 대형주 급등이 동시에 나타나는 패턴은 외국인·기관의 인덱스 매도와 함께 특정 종목 저점 매수 수급이 혼재하고 있음을 시사한다. 전반적으로 개인 투자자 중심의 패닉 셀링이 지수를 끌어내린 것으로 추정된다.\n5. 오늘 주목할 포인트는 코스피 **8,471p** 지지 여부와 삼성전자·바이오 대형주의 반등 지속성이다. 낙폭 과대 인식에 의한 반등인지, 실질적 수급 전환인지를 거래량과 외국인 동향으로 확인해야 한다.",
    "us": "미국 시장 분석:\n1. **다우 51,848p(+0.35%)** 는 소폭 상승한 반면, **S&P500 7,358p(-0.1%)** 는 보합권, **나스닥 25,476p(-0.43%)** 는 소폭 하락하며 지수 간 차별화가 나타났다. 미국 시장은 한국 대비 안정적인 흐름을 유지하고 있다.\n2. 빅테크 전반이 약보합세를 보였다. **MSFT -2.27%**, **TSLA -1.59%**, **META -0.81%**, **NVDA -0.52%**, **AAPL -0.41%** 순으로 하락했으며, **GOOGL -0.24%** 로 상대적으로 낙폭이 작았다. 기술주 섹터 전반에 매도 압력이 소폭 유지되고 있다.\n3. **미국 10년물 금리 4.402%(-1.1%)**, **30년물 4.856%(-0.92%)** 로 장기 금리가 하락하며 채권 매수 심리가 유입되고 있다. 금리 하락은 위험 자산에 긍정적이나, 원자재 동반 급락을 감안하면 경기 둔화 우려가 반영된 것으로 해석된다.\n4. **달러 인덱스 101.584(+0.17%)** 로 달러는 소폭 강세를 유지하고 있다. 달러 강세는 원/달러 환율 상승 압력으로 이어져 국내 외국인 수급에 부정적으로 작용할 수 있다.\n5. 미국 시장이 보합권을 유지하는 점은 한국 시장의 추가 급락 가능성을 다소 제한하는 요인이나, 원자재 급락과 원화 약세가 지속될 경우 국내 수출주 및 소재 섹터 중심으로 추가 하방 압력이 불가피하다.",
    "sectors": "상승 섹터:\n1. 반도체/IT - **삼성전자 +9.84%**, **SK하이닉스 +0.98%** 로 반도체 대형주 중심의 강한 저가 매수세가 유입되며 섹터 내 반등을 주도했다.\n2. 바이오/헬스케어 - **삼성바이오로직스 +8.8%**, **셀트리온 +7.6%** 등 바이오 대형주가 지수 하락 속 강한 상대 강도를 보이며 방어적 매수세가 집중됐다.\n3. 방산 - **한화 +1.96%** 로 지수 급락 속에서도 플러스를 유지하며 방산 섹터의 상대적 견고함이 확인됐다.\n하락/주의 섹터:\n1. 원자재/에너지 - **유가 WTI -4.56%**, **브렌트유 -5.14%** 급락으로 에너지 관련 종목 전반에 심각한 하방 압력이 예상된다.\n2. 귀금속/소재 - **은 -7.09%**, **금 -2.81%** 의 급락은 글로벌 위험 회피와 함께 소재 섹터 전반의 투자 심리 악화를 반영한다.\n3. 기술 성장주(미국) - **MSFT -2.27%**, **TSLA -1.59%** 등 성장주 중심의 매도세가 나타나며 고밸류 기술주에 대한 경계심이 지속되고 있다.\n중립 관망:\n1. 금융 - 금리 하락과 환율 불안이 혼재하며 뚜렷한 방향성 없이 관망 국면이 예상된다.\n2. 소비재 - 환율 부담과 경기 불확실성으로 인해 당분간 뚜렷한 모멘텀을 기대하기 어렵다.",
    "holdings": "내 보유종목 액션:\n1. **삼성전자 340,500원(+9.84%)** - 코스피 전체가 **-7.06%** 급락하는 환경에서 10% 가까운 단일 세션 급등은 이례적인 저가 매수 집중 신호다. 단기 급등에 따른 차익 실현 물량 출회 가능성을 염두에 두고, 일부 비중 조절 또는 보유 유지 전략을 검토할 것을 권고한다.\n2. **SK하이닉스 2,580,000원(+0.98%)** - 지수 대비 상대적으로 안정적인 소폭 상승을 기록했다. 반도체 섹터 전반이 저가 매수 구간으로 인식되고 있으나, 코스피 지수 불안정성이 해소되기 전까지 신규 매수보다는 현 포지션 유지 및 지지선 확인이 우선이다.",
    "picks": "관심 분야 (데이터 기반):\n1. **삼성바이오로직스(바이오)**: 코스피 **-7.06%** 급락 장에서 **+8.8%** 상승하며 강한 수급 집중이 확인됐다. 지수 하락 시 상대 강도가 뛰어난 종목으로, 반등 국면에서 선도주 역할 가능성에 주목할 필요가 있다.\n2. **셀트리온(바이오)**: **+7.6%** 상승으로 바이오 섹터 내 수급이 견고하다. 시장 전반의 불안 속에서도 방어적 성격을 보이며 중장기 포트폴리오 구성 시 고려할 수 있는 종목이다.\n3. **한화(방산)**: **+1.96%** 로 지수 하락 속 방어력이 돋보인다. 방산 섹터는 매크로 불확실성이 높을수록 안전자산 성격이 부각되는 경향이 있어 포트폴리오 헤지 수단으로 주목할 수 있다.\n4. **미국채(채권)**: **10년물 금리 4.402%(-1.1%)** 하락은 채권 가격 상승을 의미한다. 원자재 급락과 경기 불확실성 환경에서 채권 관련 자산은 리스크 헤지 수단으로 유효하다.",
    "do": "오늘 할 것:\n1. **삼성전자(+9.84%)** 단기 급등에 대한 차익 실현 여부를 검토하고, 코스피 **8,471p** 지지선 확인 후 추가 포지션 조정 계획을 수립한다.\n2. 16개 보유 종목 전반의 손익 현황을 점검하고, 코스피 **-7.06%** 급락 구간에서 특히 낙폭이 큰 종목은 손절 기준선 재설정을 고려한다.\n3. **달러/원 1,539.63원** 환율 추이를 지속 모니터링하며, 환율이 추가 상승할 경우 외국인 이탈 가능성을 반영한 리스크 관리 시나리오를 준비한다.\n4. 유가(**WTI -4.56%**)와 원자재 전반의 급락이 국내 관련 섹터에 미치는 영향을 분석하고, 에너지·소재 관련 보유 종목 비중을 재평가한다.",
    "dont": "오늘 하지 말 것:\n1. 코스피 **-7.06%** 급락 이후 단순 반등 기대만으로 무분별한 저가 매수에 나서지 말 것. 시장 변동성이 극도로 높은 상황에서 추가 하락 여지를 반드시 고려해야 한다.\n2. **삼성전자 +9.84%** 등 단일 종목 급등에 추격 매수하지 말 것. 지수 전반 급락 속 단일 종목 급등은 변동성 확대의 신호일 수 있으며 고점 매수 위험이 크다.\n3. **은 -7.09%**, **유가 -4.56%** 등 원자재 급락을 이유로 해당 섹터에 역발상 매수를 서두르지 말 것. 하락 추세가 확인되기 전까지 추가 낙폭 가능성이 열려 있다.\n4. 포트폴리오 **16개 종목** 전체를 단기간에 재편하려 하지 말 것. 패닉 장세에서 감정적 의사결정은 불필요한 손실을 확정시킬 수 있으므로 기준 없는 일괄 매도는 자제해야 한다.",
    "risk_level": 4
  },
  "youtube": [
    {
      "name": "한국경제TV",
      "type": "media",
      "videoId": "r3e3nhTTPaI",
      "title": "마이크론, '깜짝실적' 시간외 폭등…코스피 상승 기대 #코스피전망 #코스피급락 #반등예상 #매수포인트 #마이크론 #어닝서프라이즈",
      "updated": "2026-06-24T23:06:09+00:00",
      "summary": "# 핵심 주제\n마이크론의 긍정적 실적 발표가 코스피 상승을 견인할 것으로 예상되는 상황에서 투자자들의 매수 기회를 모색하는 내용\n\n# 주목 키워드\n- 마이크론 (어닝서프라이즈)\n- 코스피 상승 기대\n- 시간외 폭등\n- 매수포인트\n- 반등예상",
      "isNew": true
    },
    {
      "name": "한국경제TV",
      "type": "media",
      "videoId": "_wnA_DtDT0M",
      "title": "메모리 반도체 호황이 계속되는 이유ㅣ한지숙 DS자산운용 ETF팀 부장",
      "updated": "2026-06-24T23:26:51+00:00",
      "summary": "# 핵심 주제\n메모리 반도체 산업의 지속적인 호황 현상과 그 배경을 전문가 관점에서 분석한 내용\n\n# 주목 키워드\n- 메모리 반도체\n- 호황 (지속성)\n- DS자산운용\n- ETF 투자 관점",
      "isNew": true
    },
    {
      "name": "한국경제TV",
      "type": "media",
      "videoId": "u3T7YiRxJZg",
      "title": "6월 25일 글로벌 1분 시황✅ #당잠사 #굿모닝한경글로벌마켓 #1분시황 #SHORTS",
      "updated": "2026-06-24T23:18:12+00:00",
      "summary": "[ 핵심 메시지 ]\n\n- 마이크론의 강한 실적 발표로 AI 메모리 수요의 현실성이 입증되었으며 HBM 물량 완판으로 가격 결정력 확보\n- 반도체 업계 전반적으로 가격 인상 추세가 확산되고 있으며 메모리부터 파운드리까지 수익성 개선 중\n- SK 하이닉스의 나스닥 상장 추진과 함께 한국 반도체 기업들의 실적 개선 기대감이 높아지는 상황\n\n[ 주목 섹터/종목 ]\n\n- 반도체 메모리 - 마이크론의 분기 매출 4배 증가와 HBM 완판으로 메모리 칩 수급 부족 심화 예상\n- SK 하이닉스 - 나스닥 상장을 통한 45조원 조달 및 글로벌 시장 진출 강화로 실적 개선 가능성\n- 파운드리 및 반도체 장비 - TSMC의 가격 인상 결정으로 업계 전반적인 마진율 개선 추세\n\n[ 매수 시그널 ]\n\n- 마이크론 실적 발표 이후 시간외 거래에서 주가 12% 급등으로 긍정적 심리 형성\n- SK 하이닉스 나스닥 상장 공식화로 글로벌 투자자들의 관심 증대\n- 코스피 야간 선물이 5% 이상 상승하며 한국 반도체주에 대한 매수 심리 확산\n\n[ 매도/주의 ]\n\n- 원달러 환율이 17년 만에 최고치를 기록하며 환율 리스크 상존\n- 달러 인덱스가 13개월 만에 최고치를 찍으며 강달러 기조 지속 가능성\n- 국제 유가 하락과 금리 안정에도 불구하고 지정학적 불확실성으로 인한 변동성 위험\n\n[ 오늘 액션 ]\n\n- 반도체 메모리 관련 종목의 기술적 매수 신호 확인 후 진입 검토\n- SK 하이닉스 나스닥 상장 일정과 시장 반응 모니터링\n- 환율 변동성에 대비하여 포지션 규모 조절\n- 글로벌 반도체 업황 개선 추세 지속 여부를 주시하며 단기 수익 실현 기회 포착",
      "isNew": true
    },
    {
      "name": "한국경제TV",
      "type": "media",
      "videoId": "m7t9p089yWw",
      "title": "[한상춘의지금세계는] 韓 증시, 잭슨홀 미팅보다 더 급한 것 있다ㅣ외국인 K-엑소더스 조짐, 코스피 5000 의지 있나?ㅣ 한상춘 한국경제신문 논설위원",
      "updated": "2026-06-24T23:18:03+00:00",
      "summary": "# 핵심 주제\n한국 증시가 잭슨홀 미팅보다 더 시급한 외국인 자본 이탈 문제에 직면해 있으며, 코스피 5000 회복이 가능한지가 관건이다.\n\n# 주목 키워드\n- 외국인 K-엑소더스 (외국인 자본 이탈)\n- 코스피 5000\n- 잭슨홀 미팅\n- 한국 증시의 긴급 과제",
      "isNew": true
    },
    {
      "name": "한국경제TV",
      "type": "media",
      "videoId": "YE8EyfyzmHY",
      "title": "마이크론 '어닝 서프라이즈'…매출 5배 급증, 시간외 주가 10%↑ #코스피급락 #변동성 #반등 #코스피전망#마이크론 #어닝서프라이즈",
      "updated": "2026-06-24T23:02:51+00:00",
      "summary": "# 핵심 주제\n마이크론의 실적 호조(매출 5배 급증)로 인한 긍정적 어닝 서프라이즈가 시간외 주가를 10% 상승시키며 코스피 변동성에 영향을 미치고 있다.\n\n# 주목 키워드\n- 어닝 서프라이즈\n- 매출 5배 급증\n- 시간외 주가 10% 상승\n- 코스피 급락\n- 변동성\n- 반등",
      "isNew": true
    },
    {
      "name": "한국경제TV",
      "type": "media",
      "videoId": "4_on9NUGw-8",
      "title": "마이크론 '어닝 서프라이즈'...뉴욕증시 혼조 마감ㅣ 뉴욕인사이트_김선형 ㅣ260625",
      "updated": "2026-06-24T22:12:55+00:00",
      "summary": "# 핵심 주제\n마이크론의 긍정적 실적 발표에도 불구하고 뉴욕증시가 혼조로 마감하며 시장의 선별적 반응을 보였다.\n\n# 주목 키워드\n- 마이크론 (어닝 서프라이즈)\n- 뉴욕증시 (혼조 마감)\n- 실적 발표",
      "isNew": true
    },
    {
      "name": "한국경제TV",
      "type": "media",
      "videoId": "Oo88uSg2yhI",
      "title": "[🔴06/25 #당잠사] 마이크론 실적 발표 | 알파벳, 다우 편입에도 인재 이탈·제미나이 연기에 하락 | 오픈AI·브로드컴, 자체 AI칩 공개 | #마이크론 #구글 #브로드컴",
      "updated": "2026-06-24T21:16:29+00:00",
      "summary": "[ 핵심 메시지 ]\n\n- 마이크론의 역대급 실적 발표(매출 414.6억 달러, 주당순익 25.1달러)가 반도체 섹터 전반에 강력한 랠리 신호 제공\n- 메모리 공급 부족이 2028년까지 지속될 것으로 예상되어 AI 주도 상승 사이클 계속될 가능성 높음\n- 강달러 흐름 지속(원달러 1,542.7원, 27거래일 연속 1,500원 이상)으로 수출주 부담 가중\n\n[ 주목 섹터/종목 ]\n\n- 반도체 섹터 - 마이크론 호실적으로 저점 매수 기회 형성, 과거 18번 중 88%가 한 달 내 낙폭 회복\n- 메모리칩 관련주(SK하이닉스, TSMC) - 가격 결정력 강화 및 공급 부족 지속으로 수익성 개선 예상\n- AI 칩 개발사(브로드컴, 퀄컴) - 맞춤형 AI칩 개발로 엔비디아 독점 구조 견제 및 새로운 성장 동력 확보\n\n[ 매수 시그널 ]\n\n- 마이크론 4분기 가이던스(매출 490~510억 달러) 상향으로 반도체 섹터 강세 지속 신호\n- 마이크론 실적 이후 위험자산 선호 심리 회복으로 비트코인 등 암호화폐 반등 시작\n- 기술주 조정 국면에서 저점 매수 기회 형성, JP모건 S&P500 목표치 상향(7,600→7,800포인트)\n\n[ 매도/주의 ]\n\n- 강달러 지속으로 한국 수출주 환율 부담 심화, 외국인 자금 4일 연속 11조원 이상 순매도\n- 금값 급락(온스당 4,150달러, 연초 대비 20% 이상 하락)으로 안전자산 선호 약화\n- 알파벳 다우지수 편입에도 불구하고 AI 인력 이탈 및 제미나이 3.5 출시 연기로 경쟁력 약화 우려\n- 유가 급락(WTI 70달러 이하)으로 에너지주 부담, 중동 공급 중단 사태 최악 국면 통과\n\n[ 오늘 액션 ]\n\n- 반도체 섹터 저점 매수 검토, 특히 마이크론 실적 이후 섹터 랠리 탄승 기회 포착\n- 강달러 환경에서 수출주 회피하고 내수 및 AI 관련 기술주 비중 조정\n- SK하이닉스 미국 ADR 상장(최대 45조원 조달) 동향 모니터링으로 국내 반도체주 변동성 대비\n- 마이크론 시간외 거래 13% 이상 상승 추세 확인 후 추가 상승 여력 판단",
      "isNew": true
    },
    {
      "name": "한국경제TV",
      "type": "media",
      "videoId": "5S1a2-RN408",
      "title": "당신의 선택은? 매수📈 or 매도📉 주간랭킹전🔥START! 1등에게 상품권 5만원! ｜차트왕선발전 EP.7",
      "updated": "2026-06-24T20:38:01+00:00",
      "summary": "# 핵심 주제\n주식 매수/매도 선택에 대한 주간 랭킹 경쟁 프로그램으로, 투자 판단 능력을 겨루는 콘텐츠입니다.\n\n# 주목 키워드\n- 매수 vs 매도 (투자 선택)\n- 주간 랭킹전 (경쟁 형식)\n- 상품권 5만원 (인센티브)\n- 차트왕선발전 (프로그램명)",
      "isNew": true
    },
    {
      "name": "한국경제TV",
      "type": "media",
      "videoId": "49hmi9r6d3o",
      "title": "마이크론 실적 발표 D-day, 글로벌 반도체 위기 or 기회?ㅣ손석우ㅣ윤진ㅣ김태성",
      "updated": "2026-06-24T15:06:22+00:00",
      "summary": "# 핵심 주제\n마이크론의 실적 발표를 통해 글로벌 반도체 산업이 위기 상황인지 기회 국면인지를 판단하는 것이 투자의 핵심이다.\n\n# 주목 키워드\n- 마이크론 실적 발표\n- 글로벌 반도체 산업\n- 위기 vs 기회",
      "isNew": true
    },
    {
      "name": "연합뉴스경제TV",
      "type": "media",
      "videoId": "I-9f-UbFq_A",
      "title": "트럼프의 戰後 행보 난관…MOU 후폭풍에 민심 이반·지지층 분열",
      "updated": "2026-06-24T23:12:15+00:00",
      "summary": "# 핵심 주제\n트럼프의 전후 행보가 MOU 후폭풍으로 인한 민심 이반과 지지층 분열로 인해 난관에 직면하고 있다.\n\n# 주목 키워드\n- 트럼프 (정치적 리더십 변화)\n- MOU (양해각서 관련 정책/합의)\n- 민심 이반 (대중 지지도 하락)\n- 지지층 분열 (정치적 결집력 약화)",
      "isNew": true
    },
    {
      "name": "연합뉴스경제TV",
      "type": "media",
      "videoId": "BqxHWG3j2GM",
      "title": "이란은 IAEA사찰단 미정이라는데…트럼프 \"미국인도 포함될것\"",
      "updated": "2026-06-24T23:07:09+00:00",
      "summary": "# 핵심 주제\n이란의 IAEA 사찰단 구성을 둘러싼 미국과 이란의 입장 차이가 향후 핵 협상과 중동 정세에 영향을 미칠 수 있다.\n\n# 주목 키워드\n- **이란 핵 문제** (IAEA 사찰)\n- **미국-이란 갈등**\n- **트럼프 정책**\n- **국제 핵 감시 체계**",
      "isNew": true
    },
    {
      "name": "연합뉴스경제TV",
      "type": "media",
      "videoId": "o25irjpMF2I",
      "title": "美국무 \"호르무즈 통행료 없을 것…美·이란 협상 29·30일\"",
      "updated": "2026-06-24T22:58:21+00:00",
      "summary": "# 핵심 주제\n미국이 호르무즈 해협의 통행료 부과를 거부하며 이란과의 협상을 29~30일에 진행할 예정이다.\n\n# 주목 키워드\n- 호르무즈 해협 (유가, 해운비 영향)\n- 미·이란 협상 (지정학적 리스크)\n- 통행료 (에너지 가격 변동성)",
      "isNew": true
    },
    {
      "name": "연합뉴스경제TV",
      "type": "media",
      "videoId": "4Tj07h8lLuM",
      "title": "🔴[생방송] SK하이닉스, 7월 ADR 상장 | 삼전닉스 독주, 어디까지 갈까?  |  마켓포커스 260625",
      "updated": "2026-06-24T22:52:32+00:00",
      "summary": "# 핵심 주제\nSK하이닉스의 7월 ADR 상장과 삼성전자·SK하이닉스의 반도체 시장 독주 현황을 분석하는 내용입니다.\n\n# 주목 키워드\n- SK하이닉스 ADR 상장 (7월)\n- 삼성전자·SK하이닉스 독주\n- 반도체 시장 점유율",
      "isNew": true
    },
    {
      "name": "연합뉴스경제TV",
      "type": "media",
      "videoId": "StQrJojMqSQ",
      "title": "이스라엘, 이란 압박에도 '레바논 철군 불가' 요지부동",
      "updated": "2026-06-24T22:51:46+00:00",
      "summary": "# 핵심 주제\n이스라엘이 이란의 압박에도 불구하고 레바논에서의 군사 주둔을 지속하겠다는 입장을 고수하고 있다.\n\n# 주목 키워드\n- 이스라엘\n- 이란\n- 레바논\n- 군사 긴장\n- 중동 지정학적 리스크",
      "isNew": true
    },
    {
      "name": "연합뉴스경제TV",
      "type": "media",
      "videoId": "4AKvDOn8S98",
      "title": "\"현대차 노조도 파업할까\"…투표 결과 '찬성 86.65%'",
      "updated": "2026-06-24T22:45:20+00:00",
      "summary": "**핵심 주제:**\n현대차 노조가 파업 찬성 투표에서 86.65%의 높은 찬성률을 기록하며 실제 파업 가능성이 높아졌다.\n\n**주목 키워드:**\n- 현대차 노조\n- 파업 투표\n- 86.65% 찬성률\n- 파업 임박",
      "isNew": true
    },
    {
      "name": "연합뉴스경제TV",
      "type": "media",
      "videoId": "uRttU82CkvM",
      "title": "스페이스X 급락에…머스크, '조만장자' 타이틀 열흘여 만에 반납",
      "updated": "2026-06-24T22:38:09+00:00",
      "summary": "# 핵심 주제\n스페이스X의 주가 급락으로 인해 엘론 머스크가 세계 최고 부자 지위를 10일 만에 잃었다.\n\n# 주목 키워드\n- 스페이스X 급락\n- 엘론 머스크\n- 조만장자(세계 최고 부자)\n- 자산 변동성",
      "isNew": true
    },
    {
      "name": "연합뉴스경제TV",
      "type": "media",
      "videoId": "slwlVaabYms",
      "title": "트럼프 \"낮은 금리, 모든 것 해결…호르무즈 통행료 수용 불가\"",
      "updated": "2026-06-24T22:07:32+00:00",
      "summary": "# 핵심 주제\n트럼프 전 대통령이 낮은 금리 정책의 중요성을 강조하면서 동시에 호르무즈 해협 통행료 부과에 반대 입장을 표명했습니다.\n\n# 주목 키워드\n- **금리 인하** (경제 정책)\n- **호르무즈 해협** (지정학적 리스크)\n- **통행료** (무역/에너지 비용)\n- **트럼프** (정책 방향성)",
      "isNew": true
    },
    {
      "name": "연합뉴스경제TV",
      "type": "media",
      "videoId": "xsq-iaavsu4",
      "title": "마이크론이 좌지우지한 하루…뉴욕증시 혼조 마감",
      "updated": "2026-06-24T22:02:44+00:00",
      "summary": "# 핵심 주제\n마이크론의 실적 발표가 뉴욕증시 전체 방향성을 결정하며 시장이 혼조로 마감했다.\n\n# 주목 키워드\n- 마이크론 (Micron)\n- 뉴욕증시\n- 혼조 마감\n- 개별 종목의 영향력",
      "isNew": true
    },
    {
      "name": "연합뉴스경제TV",
      "type": "media",
      "videoId": "bizbox372XM",
      "title": "마이크론 분기 매출 4배로 껑충, 최고기록 또 갈아치워…시간외 15% 급등",
      "updated": "2026-06-24T21:40:13+00:00",
      "summary": "# 핵심 주제\n마이크론의 분기 매출이 4배 증가하며 사상 최고 기록을 경신함에 따라 시간외 거래에서 주가가 15% 급등했다.\n\n# 주목 키워드\n- 마이크론 (Micron)\n- 분기 매출 4배 증가\n- 사상 최고 기록 경신\n- 시간외 거래 15% 급등",
      "isNew": true
    },
    {
      "name": "매일경제TV",
      "type": "media",
      "videoId": "-gP840WuM6Y",
      "title": "마이크론 실적이 증명, 반도체 매수 타이밍ㅣ매아리",
      "updated": "2026-06-24T22:18:24+00:00",
      "summary": "# 핵심 주제\n마이크론의 실적 개선이 반도체 산업의 회복 신호를 보여주며 현재가 반도체 주식 매수의 적절한 시점임을 시사한다.\n\n# 주목 키워드\n- 마이크론 실적\n- 반도체 산업\n- 매수 타이밍\n- 회복 신호",
      "isNew": true
    },
    {
      "name": "경제사냥꾼",
      "type": "yt",
      "videoId": "WUpw81yDc9s",
      "title": "삼성전자 90조 '자사주 매입'이 주가에 미치는 진짜 영향",
      "updated": "2026-06-24T23:00:39+00:00",
      "summary": "[ 핵심 요약 ]\n\n- 삼성전자의 90조원 자사주 매입은 직원 성과급과 PSU 지급을 위한 것으로, 단순 주가 부양이 아닌 복합적 수급 이벤트\n- 3년에 걸친 매입으로 전체 보통주의 약 5%에 해당하는 물량이 시장 수급에 실질적 영향을 미칠 수 있음\n- 삼성 자사주 매입이 활성화되면 코스피가 하이닉스 중심에서 삼성과 하이닉스 양축 구조로 전환될 가능성\n\n[ 주요 내용 ]\n\n- 자사주 매입은 회사가 자신의 주식을 시장에서 사서 보유하는 것이고, 자사주 소각은 그 주식을 완전히 없애는 것으로 구분됨\n\n- 삼성전자가 자사주를 매입하는 이유는 반도체 부문 특별 경영 성과급과 성과 조건부 주식(PSU)을 지급할 물량이 부족하기 때문\n\n- 직원들이 받은 주식에는 1~2년의 매도 제한이 있어 단기적으로 시장 공급 물량이 감소하는 구조가 형성됨\n\n- 2024년 10조원 자사주 매입 발표 이후 삼성전자 주가가 약 68% 상승했으나, 실제 중요한 변수는 HBM4와 파운드리 실적 동반 여부임",
      "isNew": true
    },
    {
      "name": "경제사냥꾼",
      "type": "yt",
      "videoId": "wp6_EqW7F9E",
      "title": "\"스페이스X와 63억 달러 계약?!\" 제2의 엔비디아 될 수 있다는 '기업' 정체",
      "updated": "2026-06-24T21:00:17+00:00",
      "summary": "[ 핵심 요약 ]\n\n- 스페이스 X가 AI 인프라 임대 사업으로 리플렉션 AI와 63억 달러 규모 계약을 체결하여 미래 매출이 확보된 구조\n- 엔비디아는 AI 칩을 판매하고 스페이스 X는 그 칩이 탑재된 데이터센터 연산 능력을 임대하면서 AI 경쟁에서 양쪽 모두 수익 창출\n- 신세계 그룹이 리플렉션 AI와 국내 250MW급 AI 데이터센터 구축 협약으로 한국 메모리 반도체 수요 증가 기대\n\n[ 주요 내용 ]\n\n- 리플렉션 AI는 구글 딥마인드 출신 스타트업으로 엔비디아 직접 투자사이며 기업 가치가 80억 달러에서 250억 달러로 상승 중\n- 스페이스 X 콜로서스 데이터센터 외부 수주만 700억 달러 규모로 엔스로픽 월 12억 5천만 달러, 구글 월 9억 2천만 달러 등 이미 계약된 상태\n- 신세계가 리플렉션 AI와 협력하여 이마트 유통 전 과정에 AI를 이식하고 미국 정부 AI 수출 사례로 인정받음\n- SK 하이닉스가 엔비디아 주력 HBM 공급사로서 AI 데이터센터 확대에 따른 한국 메모리 반도체의 중장기 수요 증가 전망",
      "isNew": false
    },
    {
      "name": "경제사냥꾼",
      "type": "yt",
      "videoId": "bHSBISpQ93c",
      "title": "SK하이닉스 vs SK스퀘어' 월가가 선택했다는 종목은?",
      "updated": "2026-06-24T16:00:00+00:00",
      "summary": "[ 핵심 요약 ]\n\n- SK 하이닉스는 월가가 선택한 종목으로 미국 ADR 상장 추진 중이며 마이크론과의 직접 비교를 통한 재평가 가능성이 높음\n\n- 최근 폭락은 실적 악화가 아닌 과도한 자금 집중으로 인한 수급 충격이며 HBM 수요 기반은 여전히 견고함\n\n- SK 스퀘어와 하이닉스는 성격이 다르므로 무분별한 저가 매수보다 7월 반도체 실적과 빅테크 케펙스 가이던스 확인이 필수\n\n[ 주요 내용 ]\n\n- 코스피 역대 최대 낙폭 장에서 하이닉스가 코스피 시총 1위까지 올라섰으나 단일 종목 레버리지 ETF 매물과 겹치면서 지수 전체가 함께 하락\n\n- 글로벌 빅테크가 올해 AI 인프라에 약 천조원 규모 투자를 계획 중이며 이 자금이 결국 메모리 수요로 이어지는 구조\n\n- 증권사들이 하이닉스 목표가 380만원에서 430만원, SK 스퀘어 목표가 270만원으로 유지 또는 상향 조정\n\n- 골드만 삭스는 메모리 호황이 예상보다 더 오래 지속되며 메모리 주의 밸류에이션 자체가 상승할 수 있다고 평가",
      "isNew": false
    },
    {
      "name": "경제사냥꾼",
      "type": "yt",
      "videoId": "9n9usdXS6Vs",
      "title": "코스피 1만 오기 전, 개인들이 가장 많이 털리는 '하락장'이 꼭 오는 이유",
      "updated": "2026-06-24T15:00:24+00:00",
      "summary": "[ 핵심 요약 ]\n\n- 코스피가 상승장에서 반복적으로 급락하는 것은 구조적 현상이며, 같은 폭락을 맞아도 개인투자자가 특히 큰 손실을 입는 이유는 신용거래(빚)에 있음\n\n- 신용거래는 상승장에서는 수익을 배수로 늘리지만 하락장에서는 강제 매도(반대 매매)로 인해 손실을 배수로 증폭시키고 회복 기회까지 빼앗음\n\n- 코스피가 장기적으로 상승한다는 믿음과 빚내서 추격 매수한다는 행동은 완전히 다른 문제이며, 폭락장 생존을 위해서는 자신의 신용거래 규모 파악과 시장 자금 흐름 모니터링이 필수\n\n[ 주요 내용 ]\n\n- 6월 22일 코스피 9,114로 사상 최고치 기록 후 6월 23일 910포인트(9.99%) 폭락, 이는 미국 빅테크 약세, SK하이닉스 미국 상장 지연, MSCI 선진국 지수 편입 미뤄짐 등 악재가 동시에 터진 결과\n\n- 6월 22일 기준 신용거래 잔고가 38조 5,311억 원으로 역대 최대 규모이며, 삼성전자와 SK하이닉스에만 6조 원 이상의 신용거래 잔고가 집중되어 있음\n\n- 2월 미국-이란 전쟁 위기 당시 신용거래를 사용한 계좌의 평균 손실률이 일반 계좌보다 3배 이상 컸으며, 20대 소액 신용거래 투자자는 일반 투자자의 3.2배 손실을 기록\n\n- 강제 매도가 연쇄적으로 발생하면서 추가 하락을 유발하는 악순환이 발생하며, 이 과정에서 개인투자자는 반등 기회를 완전히 상실하게 됨",
      "isNew": false
    }
  ]
}